{
"meta":{"test_sets":[],"test_metrics":[],"learn_metrics":[{"best_value":"Min","name":"RMSE"}],"launch_mode":"Train","parameters":"","iteration_count":1000,"learn_sets":["learn"],"name":"experiment"},
"iterations":[
{"learn":[14.61268541],"iteration":0,"passed_time":0.05692691246,"remaining_time":56.86998554},
{"learn":[14.23196558],"iteration":1,"passed_time":0.05734890965,"remaining_time":28.61710591},
{"learn":[13.86674177],"iteration":2,"passed_time":0.05761703286,"remaining_time":19.14806059},
{"learn":[13.49946468],"iteration":3,"passed_time":0.05787798946,"remaining_time":14.41161937},
{"learn":[13.16661202],"iteration":4,"passed_time":0.05824002871,"remaining_time":11.58976571},
{"learn":[12.85632158],"iteration":5,"passed_time":0.05866381755,"remaining_time":9.718639108},
{"learn":[12.56784336],"iteration":6,"passed_time":0.05902352349,"remaining_time":8.372908404},
{"learn":[12.31617801],"iteration":7,"passed_time":0.0594872704,"remaining_time":7.37642153},
{"learn":[12.01509946],"iteration":8,"passed_time":0.05976672687,"remaining_time":6.580980704},
{"learn":[11.71512571],"iteration":9,"passed_time":0.06009797467,"remaining_time":5.949699492},
{"learn":[11.43264457],"iteration":10,"passed_time":0.06035297297,"remaining_time":5.426280933},
{"learn":[11.17973129],"iteration":11,"passed_time":0.06072584548,"remaining_time":4.999761278},
{"learn":[10.93746433],"iteration":12,"passed_time":0.06102788514,"remaining_time":4.633424818},
{"learn":[10.69387075],"iteration":13,"passed_time":0.06147513216,"remaining_time":4.329605736},
{"learn":[10.4615922],"iteration":14,"passed_time":0.06174029706,"remaining_time":4.054279507},
{"learn":[10.2299235],"iteration":15,"passed_time":0.06205529496,"remaining_time":3.81640064},
{"learn":[10.01419731],"iteration":16,"passed_time":0.06240625096,"remaining_time":3.608549688},
{"learn":[9.795856918],"iteration":17,"passed_time":0.0626605826,"remaining_time":3.418482895},
{"learn":[9.60040151],"iteration":18,"passed_time":0.0630598716,"remaining_time":3.255880739},
{"learn":[9.418664989],"iteration":19,"passed_time":0.06341728589,"remaining_time":3.107447009},
{"learn":[9.249278645],"iteration":20,"passed_time":0.06385111633,"remaining_time":2.976678233},
{"learn":[9.090113396],"iteration":21,"passed_time":0.06410761462,"remaining_time":2.849874868},
{"learn":[8.909548708],"iteration":22,"passed_time":0.06456156993,"remaining_time":2.74246321},
{"learn":[8.740140208],"iteration":23,"passed_time":0.06490519264,"remaining_time":2.639477834},
{"learn":[8.59377682],"iteration":24,"passed_time":0.06530427332,"remaining_time":2.546866659},
{"learn":[8.453885414],"iteration":25,"passed_time":0.06557856316,"remaining_time":2.456673866},
{"learn":[8.317732234],"iteration":26,"passed_time":0.06587822783,"remaining_time":2.374056136},
{"learn":[8.180896085],"iteration":27,"passed_time":0.06691701258,"remaining_time":2.322976294},
{"learn":[8.053220863],"iteration":28,"passed_time":0.06731513492,"remaining_time":2.253896414},
{"learn":[7.924234474],"iteration":29,"passed_time":0.06759092475,"remaining_time":2.1854399},
{"learn":[7.818879511],"iteration":30,"passed_time":0.06784633972,"remaining_time":2.120745264},
{"learn":[7.719346395],"iteration":31,"passed_time":0.06813712945,"remaining_time":2.061148166},
{"learn":[7.624163594],"iteration":32,"passed_time":0.06847683552,"remaining_time":2.006578786},
{"learn":[7.524952543],"iteration":33,"passed_time":0.06886383294,"remaining_time":1.956543018},
{"learn":[7.424464745],"iteration":34,"passed_time":0.06923599713,"remaining_time":1.908935349},
{"learn":[7.327482321],"iteration":35,"passed_time":0.06953991177,"remaining_time":1.862124304},
{"learn":[7.238666841],"iteration":36,"passed_time":0.06984240976,"remaining_time":1.817790286},
{"learn":[7.158842395],"iteration":37,"passed_time":0.07024882372,"remaining_time":1.778404432},
{"learn":[7.074348246],"iteration":38,"passed_time":0.07055582167,"remaining_time":1.738567811},
{"learn":[6.992269093],"iteration":39,"passed_time":0.07085723633,"remaining_time":1.700573672},
{"learn":[6.925219745],"iteration":40,"passed_time":0.07121906725,"remaining_time":1.665831354},
{"learn":[6.86013671],"iteration":41,"passed_time":0.0715323985,"remaining_time":1.631619947},
{"learn":[6.786739622],"iteration":42,"passed_time":0.07187002125,"remaining_time":1.599525822},
{"learn":[6.73057926],"iteration":43,"passed_time":0.07225960199,"remaining_time":1.57000408},
{"learn":[6.666356486],"iteration":44,"passed_time":0.07250930866,"remaining_time":1.538808662},
{"learn":[6.606182832],"iteration":45,"passed_time":0.07273826547,"remaining_time":1.508528375},
{"learn":[6.547854615],"iteration":46,"passed_time":0.07296876393,"remaining_time":1.479558128},
{"learn":[6.49240675],"iteration":47,"passed_time":0.0732892618,"remaining_time":1.453570359},
{"learn":[6.431317261],"iteration":48,"passed_time":0.07415171438,"remaining_time":1.439148579},
{"learn":[6.377586395],"iteration":49,"passed_time":0.07458266985,"remaining_time":1.417070727},
{"learn":[6.327558015],"iteration":50,"passed_time":0.07492141759,"remaining_time":1.394125986},
{"learn":[6.282040317],"iteration":51,"passed_time":0.07534108146,"remaining_time":1.37352587},
{"learn":[6.237655841],"iteration":52,"passed_time":0.07570899568,"remaining_time":1.352762621},
{"learn":[6.192792003],"iteration":53,"passed_time":0.07607795155,"remaining_time":1.332773003},
{"learn":[6.150579347],"iteration":54,"passed_time":0.07652124027,"remaining_time":1.314774037},
{"learn":[6.115693845],"iteration":55,"passed_time":0.07681419665,"remaining_time":1.294867886},
{"learn":[6.078780782],"iteration":56,"passed_time":0.07704861175,"remaining_time":1.274681419},
{"learn":[6.045146957],"iteration":57,"passed_time":0.07743452585,"remaining_time":1.257643506},
{"learn":[6.008080327],"iteration":58,"passed_time":0.07768956582,"remaining_time":1.239082736},
{"learn":[5.977575734],"iteration":59,"passed_time":0.07804027181,"remaining_time":1.222630925},
{"learn":[5.948036502],"iteration":60,"passed_time":0.07827910356,"remaining_time":1.204984889},
{"learn":[5.914888282],"iteration":61,"passed_time":0.07863210121,"remaining_time":1.189627596},
{"learn":[5.884957796],"iteration":62,"passed_time":0.07901043202,"remaining_time":1.17512341},
{"learn":[5.849539885],"iteration":63,"passed_time":0.07944801244,"remaining_time":1.161927182},
{"learn":[5.821387627],"iteration":64,"passed_time":0.07995796737,"remaining_time":1.150164608},
{"learn":[5.797012279],"iteration":65,"passed_time":0.08036075636,"remaining_time":1.137226461},
{"learn":[5.768685095],"iteration":66,"passed_time":0.08078787851,"remaining_time":1.125001353},
{"learn":[5.755484587],"iteration":67,"passed_time":0.08089096116,"remaining_time":1.108681997},
{"learn":[5.731887055],"iteration":68,"passed_time":0.08126629199,"remaining_time":1.096506056},
{"learn":[5.707148487],"iteration":69,"passed_time":0.08178833018,"remaining_time":1.086616387},
{"learn":[5.685365039],"iteration":70,"passed_time":0.08213224456,"remaining_time":1.074659932},
{"learn":[5.663541834],"iteration":71,"passed_time":0.08249957544,"remaining_time":1.063327861},
{"learn":[5.638108797],"iteration":72,"passed_time":0.08281723999,"remaining_time":1.0516655},
{"learn":[5.619204893],"iteration":73,"passed_time":0.08314223783,"remaining_time":1.040401517},
{"learn":[5.598472793],"iteration":74,"passed_time":0.08346598567,"remaining_time":1.029413823},
{"learn":[5.577007075],"iteration":75,"passed_time":0.08378352522,"remaining_time":1.01863128},
{"learn":[5.562637084],"iteration":76,"passed_time":0.08402381529,"remaining_time":1.007194565},
{"learn":[5.54729991],"iteration":77,"passed_time":0.08427710527,"remaining_time":0.9961986033},
{"learn":[5.530737623],"iteration":78,"passed_time":0.08469456082,"remaining_time":0.9873884875},
{"learn":[5.513704873],"iteration":79,"passed_time":0.08571197071,"remaining_time":0.9856876632},
{"learn":[5.501575529],"iteration":80,"passed_time":0.0859930105,"remaining_time":0.9756490945},
{"learn":[5.484080734],"iteration":81,"passed_time":0.08630175845,"remaining_time":0.9661587104},
{"learn":[5.472178894],"iteration":82,"passed_time":0.08681167172,"remaining_time":0.9591120839},
{"learn":[5.458923342],"iteration":83,"passed_time":0.08709216985,"remaining_time":0.949719376},
{"learn":[5.451382371],"iteration":84,"passed_time":0.0873500848,"remaining_time":0.9402979717},
{"learn":[5.441410748],"iteration":85,"passed_time":0.08764874948,"remaining_time":0.9315227561},
{"learn":[5.434047468],"iteration":86,"passed_time":0.08777816528,"remaining_time":0.9211662632},
{"learn":[5.422107497],"iteration":87,"passed_time":0.08810470477,"remaining_time":0.9130851222},
{"learn":[5.40731265],"iteration":88,"passed_time":0.08850186879,"remaining_time":0.9059011513},
{"learn":[5.396360181],"iteration":89,"passed_time":0.08881786669,"remaining_time":0.8980473187},
{"learn":[5.383793239],"iteration":90,"passed_time":0.08916561437,"remaining_time":0.8906763018},
{"learn":[5.369605034],"iteration":91,"passed_time":0.08951352872,"remaining_time":0.8834596095},
{"learn":[5.357467333],"iteration":92,"passed_time":0.08996731736,"remaining_time":0.8774231919},
{"learn":[5.341109968],"iteration":93,"passed_time":0.0903922312,"remaining_time":0.8712272497},
{"learn":[5.330529276],"iteration":94,"passed_time":0.09085493645,"remaining_time":0.8655128157},
{"learn":[5.319862075],"iteration":95,"passed_time":0.09119555918,"remaining_time":0.8587581823},
{"learn":[5.313052243],"iteration":96,"passed_time":0.09152576532,"remaining_time":0.8520388256},
{"learn":[5.299677207],"iteration":97,"passed_time":0.09188976289,"remaining_time":0.8457608789},
{"learn":[5.287546698],"iteration":98,"passed_time":0.09224301054,"remaining_time":0.8395045707},
{"learn":[5.279803754],"iteration":99,"passed_time":0.09254884183,"remaining_time":0.8329395765},
{"learn":[5.272254612],"iteration":100,"passed_time":0.0929691307,"remaining_time":0.8275173119},
{"learn":[5.268813888],"iteration":101,"passed_time":0.09307746331,"remaining_time":0.8194466868},
{"learn":[5.258113767],"iteration":102,"passed_time":0.09336441973,"remaining_time":0.8130862573},
{"learn":[5.251018576],"iteration":103,"passed_time":0.09378087529,"remaining_time":0.8079583102},
{"learn":[5.24171237],"iteration":104,"passed_time":0.09417837265,"remaining_time":0.8027585097},
{"learn":[5.233984943],"iteration":105,"passed_time":0.09460457814,"remaining_time":0.7978914421},
{"learn":[5.226240449],"iteration":106,"passed_time":0.09492128436,"remaining_time":0.7921935228},
{"learn":[5.220541644],"iteration":107,"passed_time":0.0953111151,"remaining_time":0.7871992099},
{"learn":[5.211712096],"iteration":108,"passed_time":0.09560607147,"remaining_time":0.7815138503},
{"learn":[5.203388597],"iteration":109,"passed_time":0.09592706933,"remaining_time":0.7761371973},
{"learn":[5.196026544],"iteration":110,"passed_time":0.09621902572,"remaining_time":0.7706190438},
{"learn":[5.188716772],"iteration":111,"passed_time":0.09654098191,"remaining_time":0.7654320708},
{"learn":[5.182163132],"iteration":112,"passed_time":0.09683235497,"remaining_time":0.7600911403},
{"learn":[5.17764747],"iteration":113,"passed_time":0.09712368636,"remaining_time":0.7548384747},
{"learn":[5.170548056],"iteration":114,"passed_time":0.09737918466,"remaining_time":0.7493963341},
{"learn":[5.165901827],"iteration":115,"passed_time":0.09761093311,"remaining_time":0.7438626282},
{"learn":[5.160333668],"iteration":116,"passed_time":0.09786693141,"remaining_time":0.7386025678},
{"learn":[5.148953243],"iteration":117,"passed_time":0.09824038725,"remaining_time":0.7343052674},
{"learn":[5.144729126],"iteration":118,"passed_time":0.0985238437,"remaining_time":0.729407616},
{"learn":[5.139939946],"iteration":119,"passed_time":0.09885246651,"remaining_time":0.7249180877},
{"learn":[5.132898872],"iteration":120,"passed_time":0.09928771361,"remaining_time":0.721271903},
{"learn":[5.129073077],"iteration":121,"passed_time":0.09954667022,"remaining_time":0.7164096431},
{"learn":[5.127123916],"iteration":122,"passed_time":0.09970387751,"remaining_time":0.7108967526},
{"learn":[5.121282057],"iteration":123,"passed_time":0.1000068755,"remaining_time":0.7065001849},
{"learn":[5.114489821],"iteration":124,"passed_time":0.1003545815,"remaining_time":0.7024820705},
{"learn":[5.107777291],"iteration":125,"passed_time":0.100673871,"remaining_time":0.6983251055},
{"learn":[5.103518754],"iteration":126,"passed_time":0.1010600351,"remaining_time":0.694688273},
{"learn":[5.101133351],"iteration":127,"passed_time":0.1013098251,"remaining_time":0.6901731838},
{"learn":[5.096462705],"iteration":128,"passed_time":0.1016779477,"remaining_time":0.6865231972},
{"learn":[5.08562082],"iteration":129,"passed_time":0.1020986532,"remaining_time":0.6832756023},
{"learn":[5.080483682],"iteration":130,"passed_time":0.1024969422,"remaining_time":0.6799224641},
{"learn":[5.07437499],"iteration":131,"passed_time":0.1029709807,"remaining_time":0.6771122067},
{"learn":[5.070683732],"iteration":132,"passed_time":0.1032107708,"remaining_time":0.6728100624},
{"learn":[5.06432037],"iteration":133,"passed_time":0.1036494762,"remaining_time":0.6698540777},
{"learn":[5.057436484],"iteration":134,"passed_time":0.1038864746,"remaining_time":0.6656429672},
{"learn":[5.053254656],"iteration":135,"passed_time":0.1042744304,"remaining_time":0.6624493225},
{"learn":[5.04801663],"iteration":136,"passed_time":0.1046752194,"remaining_time":0.6593774769},
{"learn":[5.045680836],"iteration":137,"passed_time":0.1050153421,"remaining_time":0.6559653979},
{"learn":[5.041857933],"iteration":138,"passed_time":0.10533584,"remaining_time":0.6524759585},
{"learn":[5.035264888],"iteration":139,"passed_time":0.1056357547,"remaining_time":0.64890535},
{"learn":[5.028771948],"iteration":140,"passed_time":0.106040502,"remaining_time":0.6460197956},
{"learn":[5.024912247],"iteration":141,"passed_time":0.1064596242,"remaining_time":0.643256039},
{"learn":[5.02239068],"iteration":142,"passed_time":0.1068091218,"remaining_time":0.6401078141},
{"learn":[5.017110572],"iteration":143,"passed_time":0.1072250774,"remaining_time":0.6373935157},
{"learn":[5.010707886],"iteration":144,"passed_time":0.1077758237,"remaining_time":0.6355057193},
{"learn":[5.004389868],"iteration":145,"passed_time":0.1083270284,"remaining_time":0.6336389195},
{"learn":[4.997628683],"iteration":146,"passed_time":0.1086860677,"remaining_time":0.6306749369},
{"learn":[4.991497851],"iteration":147,"passed_time":0.1089396493,"remaining_time":0.6271390623},
{"learn":[4.988345253],"iteration":148,"passed_time":0.1091913143,"remaining_time":0.6236362985},
{"learn":[4.98460423],"iteration":149,"passed_time":0.1096128532,"remaining_time":0.6211395013},
{"learn":[4.982441783],"iteration":150,"passed_time":0.1098718098,"remaining_time":0.6177560695},
{"learn":[4.977461771],"iteration":151,"passed_time":0.1102321407,"remaining_time":0.6149793113},
{"learn":[4.973601586],"iteration":152,"passed_time":0.1106528046,"remaining_time":0.6125681403},
{"learn":[4.968328804],"iteration":153,"passed_time":0.1110282604,"remaining_time":0.6099344695},
{"learn":[4.9640736],"iteration":154,"passed_time":0.1112931336,"remaining_time":0.6067270834},
{"learn":[4.960865882],"iteration":155,"passed_time":0.1115171738,"remaining_time":0.6033365045},
{"learn":[4.957014156],"iteration":156,"passed_time":0.1119777124,"remaining_time":0.6012561246},
{"learn":[4.952244852],"iteration":157,"passed_time":0.1123547932,"remaining_time":0.5987514931},
{"learn":[4.949695675],"iteration":158,"passed_time":0.1127407073,"remaining_time":0.5963203451},
{"learn":[4.946584698],"iteration":159,"passed_time":0.1131542879,"remaining_time":0.5940600115},
{"learn":[4.940192834],"iteration":160,"passed_time":0.1135348687,"remaining_time":0.5916506512},
{"learn":[4.936727994],"iteration":161,"passed_time":0.1139462826,"remaining_time":0.5894258324},
{"learn":[4.932342063],"iteration":162,"passed_time":0.1143736548,"remaining_time":0.5873052089},
{"learn":[4.925830838],"iteration":163,"passed_time":0.1146679445,"remaining_time":0.584526839},
{"learn":[4.922571773],"iteration":164,"passed_time":0.1149899423,"remaining_time":0.5819187991},
{"learn":[4.918395814],"iteration":165,"passed_time":0.1153207318,"remaining_time":0.5793824719},
{"learn":[4.911142452],"iteration":166,"passed_time":0.1156711461,"remaining_time":0.5769704475},
{"learn":[4.908276131],"iteration":167,"passed_time":0.1160616852,"remaining_time":0.5747816791},
{"learn":[4.904584645],"iteration":168,"passed_time":0.1163515999,"remaining_time":0.5721194056},
{"learn":[4.89795517],"iteration":169,"passed_time":0.1167588056,"remaining_time":0.5700576978},
{"learn":[4.895556491],"iteration":170,"passed_time":0.1171612195,"remaining_time":0.5679921111},
{"learn":[4.890591233],"iteration":171,"passed_time":0.117538842,"remaining_time":0.5658265186},
{"learn":[4.884629277],"iteration":172,"passed_time":0.1179025479,"remaining_time":0.5636150702},
{"learn":[4.880550786],"iteration":173,"passed_time":0.118301212,"remaining_time":0.5615908108},
{"learn":[4.876384842],"iteration":174,"passed_time":0.118892833,"remaining_time":0.5604947842},
{"learn":[4.872638238],"iteration":175,"passed_time":0.1192721222,"remaining_time":0.5584103901},
{"learn":[4.869137118],"iteration":176,"passed_time":0.1197043693,"remaining_time":0.5565915023},
{"learn":[4.863587157],"iteration":177,"passed_time":0.1200258255,"remaining_time":0.5542765648},
{"learn":[4.858028614],"iteration":178,"passed_time":0.1204635726,"remaining_time":0.5525172797},
{"learn":[4.853838176],"iteration":179,"passed_time":0.1209410277,"remaining_time":0.5509535707},
{"learn":[4.853462329],"iteration":180,"passed_time":0.1210364437,"remaining_time":0.5476731902},
{"learn":[4.851573196],"iteration":181,"passed_time":0.1213757748,"remaining_time":0.5455240868},
{"learn":[4.848442087],"iteration":182,"passed_time":0.1218014386,"remaining_time":0.5437801933},
{"learn":[4.845547104],"iteration":183,"passed_time":0.1221471863,"remaining_time":0.5416962177},
{"learn":[4.839868817],"iteration":184,"passed_time":0.1226520996,"remaining_time":0.5403322227},
{"learn":[4.836336958],"iteration":185,"passed_time":0.1230068473,"remaining_time":0.5383202886},
{"learn":[4.831124789],"iteration":186,"passed_time":0.1233044286,"remaining_time":0.5360775426},
{"learn":[4.827407333],"iteration":187,"passed_time":0.1243584633,"remaining_time":0.5371227243},
{"learn":[4.824088918],"iteration":188,"passed_time":0.1246394614,"remaining_time":0.5348285883},
{"learn":[4.820934539],"iteration":189,"passed_time":0.1251090833,"remaining_time":0.5333597761},
{"learn":[4.816975227],"iteration":190,"passed_time":0.1253462067,"remaining_time":0.5309166556},
{"learn":[4.812340486],"iteration":191,"passed_time":0.1255768718,"remaining_time":0.5284693356},
{"learn":[4.806402747],"iteration":192,"passed_time":0.1258162036,"remaining_time":0.5260812242},
{"learn":[4.801521788],"iteration":193,"passed_time":0.1260782435,"remaining_time":0.5238096095},
{"learn":[4.797601172],"iteration":194,"passed_time":0.1264810325,"remaining_time":0.5221396469},
{"learn":[4.792694629],"iteration":195,"passed_time":0.1267252808,"remaining_time":0.5198322745},
{"learn":[4.789794613],"iteration":196,"passed_time":0.1271199449,"remaining_time":0.5181589631},
{"learn":[4.785367055],"iteration":197,"passed_time":0.1274557343,"remaining_time":0.5162600955},
{"learn":[4.780376856],"iteration":198,"passed_time":0.1278291902,"remaining_time":0.5145285493},
{"learn":[4.776691261],"iteration":199,"passed_time":0.1281839378,"remaining_time":0.5127357512},
{"learn":[4.773470753],"iteration":200,"passed_time":0.1285141023,"remaining_time":0.5108595408},
{"learn":[4.77207327],"iteration":201,"passed_time":0.1288193919,"remaining_time":0.5089003699},
{"learn":[4.767347177],"iteration":202,"passed_time":0.1292841805,"remaining_time":0.5075837036},
{"learn":[4.763983068],"iteration":203,"passed_time":0.1296638446,"remaining_time":0.5059432368},
{"learn":[4.761588849],"iteration":204,"passed_time":0.1301868828,"remaining_time":0.504871082},
{"learn":[4.758558086],"iteration":205,"passed_time":0.1306099216,"remaining_time":0.5034188241},
{"learn":[4.753678804],"iteration":206,"passed_time":0.1309391694,"remaining_time":0.5016172047},
{"learn":[4.746510889],"iteration":207,"passed_time":0.1313900414,"remaining_time":0.5002928501},
{"learn":[4.744840601],"iteration":208,"passed_time":0.1318054553,"remaining_time":0.4988426563},
{"learn":[4.741702222],"iteration":209,"passed_time":0.1322170776,"remaining_time":0.4973880538},
{"learn":[4.739352853],"iteration":210,"passed_time":0.1325417838,"remaining_time":0.4956183289},
{"learn":[4.735539287],"iteration":211,"passed_time":0.132902823,"remaining_time":0.4939972856},
{"learn":[4.730726751],"iteration":212,"passed_time":0.1333222369,"remaining_time":0.4926037579},
{"learn":[4.726416092],"iteration":213,"passed_time":0.1337267342,"remaining_time":0.4911645471},
{"learn":[4.721293082],"iteration":214,"passed_time":0.1341514397,"remaining_time":0.489808745},
{"learn":[4.718443695],"iteration":215,"passed_time":0.134506854,"remaining_time":0.4882100627},
{"learn":[4.711627962],"iteration":216,"passed_time":0.1348758932,"remaining_time":0.4866720018},
{"learn":[4.709790764],"iteration":217,"passed_time":0.1352845572,"remaining_time":0.4852868059},
{"learn":[4.706913073],"iteration":218,"passed_time":0.1355328055,"remaining_time":0.4833384525},
{"learn":[4.703846389],"iteration":219,"passed_time":0.1359270529,"remaining_time":0.4819231875},
{"learn":[4.701001135],"iteration":220,"passed_time":0.1362345925,"remaining_time":0.4802115274},
{"learn":[4.700380864],"iteration":221,"passed_time":0.13661159,"remaining_time":0.4787559325},
{"learn":[4.695837486],"iteration":222,"passed_time":0.13685263,"remaining_time":0.4768362939},
{"learn":[4.691242996],"iteration":223,"passed_time":0.1370945451,"remaining_time":0.4749346741},
{"learn":[4.690284609],"iteration":224,"passed_time":0.1373770432,"remaining_time":0.4731875933},
{"learn":[4.68827119],"iteration":225,"passed_time":0.1377329158,"remaining_time":0.4717047649},
{"learn":[4.686922425],"iteration":226,"passed_time":0.1393669883,"remaining_time":0.474584502},
{"learn":[4.686085874],"iteration":227,"passed_time":0.1397228193,"remaining_time":0.4730965635},
{"learn":[4.683230741],"iteration":228,"passed_time":0.1400196923,"remaining_time":0.471420012},
{"learn":[4.6773487],"iteration":229,"passed_time":0.140308357,"remaining_time":0.4697279779},
{"learn":[4.671462906],"iteration":230,"passed_time":0.1405579387,"remaining_time":0.4679179864},
{"learn":[4.664799601],"iteration":231,"passed_time":0.1408338952,"remaining_time":0.4662087565},
{"learn":[4.660979386],"iteration":232,"passed_time":0.1410983934,"remaining_time":0.4644741106},
{"learn":[4.656281279],"iteration":233,"passed_time":0.1414048081,"remaining_time":0.4628892435},
{"learn":[4.651997094],"iteration":234,"passed_time":0.141911638,"remaining_time":0.4619676727},
{"learn":[4.650151977],"iteration":235,"passed_time":0.1423373852,"remaining_time":0.4607871283},
{"learn":[4.648478046],"iteration":236,"passed_time":0.1426100084,"remaining_time":0.4591199847},
{"learn":[4.646364602],"iteration":237,"passed_time":0.1430437555,"remaining_time":0.4579804272},
{"learn":[4.642635873],"iteration":238,"passed_time":0.1433809199,"remaining_time":0.456539247},
{"learn":[4.640860821],"iteration":239,"passed_time":0.1436374182,"remaining_time":0.4548518242},
{"learn":[4.639446822],"iteration":240,"passed_time":0.1439300829,"remaining_time":0.4532901781},
{"learn":[4.637120072],"iteration":241,"passed_time":0.1445280789,"remaining_time":0.4526953877},
{"learn":[4.633769267],"iteration":242,"passed_time":0.1449270763,"remaining_time":0.451480645},
{"learn":[4.630491517],"iteration":243,"passed_time":0.1451631164,"remaining_time":0.4497676884},
{"learn":[4.627813333],"iteration":244,"passed_time":0.1456385299,"remaining_time":0.4488044491},
{"learn":[4.622496304],"iteration":245,"passed_time":0.1459604027,"remaining_time":0.4473745677},
{"learn":[4.618979301],"iteration":246,"passed_time":0.1462442758,"remaining_time":0.4458378125},
{"learn":[4.616563458],"iteration":247,"passed_time":0.1464892325,"remaining_time":0.4441931567},
{"learn":[4.614759385],"iteration":248,"passed_time":0.1468011888,"remaining_time":0.4427618184},
{"learn":[4.61251363],"iteration":249,"passed_time":0.1470923535,"remaining_time":0.4412770605},
{"learn":[4.608796693],"iteration":250,"passed_time":0.1474933092,"remaining_time":0.4401294365},
{"learn":[4.60847774],"iteration":251,"passed_time":0.1479758893,"remaining_time":0.4392300206},
{"learn":[4.605195659],"iteration":252,"passed_time":0.1482961371,"remaining_time":0.4378546026},
{"learn":[4.60103766],"iteration":253,"passed_time":0.1486104267,"remaining_time":0.4364699934},
{"learn":[4.599325598],"iteration":254,"passed_time":0.1489307579,"remaining_time":0.43511143},
{"learn":[4.597012808],"iteration":255,"passed_time":0.1494375879,"remaining_time":0.4343029898},
{"learn":[4.594161533],"iteration":256,"passed_time":0.1497460858,"remaining_time":0.4329235088},
{"learn":[4.592197259],"iteration":257,"passed_time":0.1500778336,"remaining_time":0.4316191959},
{"learn":[4.58952828],"iteration":258,"passed_time":0.1504801226,"remaining_time":0.4305242118},
{"learn":[4.585816572],"iteration":259,"passed_time":0.1509159114,"remaining_time":0.4295299016},
{"learn":[4.582934052],"iteration":260,"passed_time":0.1513973248,"remaining_time":0.4286690538},
{"learn":[4.582234842],"iteration":261,"passed_time":0.1516877812,"remaining_time":0.4272732158},
{"learn":[4.57571562],"iteration":262,"passed_time":0.1521347782,"remaining_time":0.4263244546},
{"learn":[4.571197349],"iteration":263,"passed_time":0.1525321506,"remaining_time":0.4252411471},
{"learn":[4.56723703],"iteration":264,"passed_time":0.1529676894,"remaining_time":0.4242688743},
{"learn":[4.560335567],"iteration":265,"passed_time":0.1534627277,"remaining_time":0.4234648201},
{"learn":[4.554709345],"iteration":266,"passed_time":0.1537921422,"remaining_time":0.4222083904},
{"learn":[4.552806306],"iteration":267,"passed_time":0.1542638474,"remaining_time":0.4213475235},
{"learn":[4.550766241],"iteration":268,"passed_time":0.1545318456,"remaining_time":0.4199359819},
{"learn":[4.549216045],"iteration":269,"passed_time":0.1549015931,"remaining_time":0.4188080111},
{"learn":[4.547687452],"iteration":270,"passed_time":0.1552160494,"remaining_time":0.4175369004},
{"learn":[4.545642435],"iteration":271,"passed_time":0.1555063808,"remaining_time":0.4162082545},
{"learn":[4.543930359],"iteration":272,"passed_time":0.1560010025,"remaining_time":0.4154312411},
{"learn":[4.541029943],"iteration":273,"passed_time":0.1564363329,"remaining_time":0.4144991887},
{"learn":[4.537781449],"iteration":274,"passed_time":0.1568225804,"remaining_time":0.4134413482},
{"learn":[4.53066128],"iteration":275,"passed_time":0.1571552448,"remaining_time":0.4122478161},
{"learn":[4.526763956],"iteration":276,"passed_time":0.1575338673,"remaining_time":0.411180455},
{"learn":[4.522036004],"iteration":277,"passed_time":0.1581686547,"remaining_time":0.4107833407},
{"learn":[4.515307629],"iteration":278,"passed_time":0.1584196114,"remaining_time":0.4093926158},
{"learn":[4.51109143],"iteration":279,"passed_time":0.1586577765,"remaining_time":0.4079771395},
{"learn":[4.508233494],"iteration":280,"passed_time":0.1589288997,"remaining_time":0.4066543731},
{"learn":[4.502555629],"iteration":281,"passed_time":0.1592396059,"remaining_time":0.4054398477},
{"learn":[4.500081355],"iteration":282,"passed_time":0.1595878953,"remaining_time":0.404326929},
{"learn":[4.495281743],"iteration":283,"passed_time":0.1598613934,"remaining_time":0.403030837},
{"learn":[4.492138869],"iteration":284,"passed_time":0.1603632234,"remaining_time":0.4023147535},
{"learn":[4.491708261],"iteration":285,"passed_time":0.1606952212,"remaining_time":0.4011761817},
{"learn":[4.489398865],"iteration":286,"passed_time":0.1609417196,"remaining_time":0.3998308225},
{"learn":[4.485796373],"iteration":287,"passed_time":0.1612137178,"remaining_time":0.3985561356},
{"learn":[4.479542205],"iteration":288,"passed_time":0.1615993819,"remaining_time":0.3975680294},
{"learn":[4.475986993],"iteration":289,"passed_time":0.1620501289,"remaining_time":0.3967434189},
{"learn":[4.468661855],"iteration":290,"passed_time":0.1623127521,"remaining_time":0.3954630283},
{"learn":[4.463785664],"iteration":291,"passed_time":0.1625942086,"remaining_time":0.3942352728},
{"learn":[4.460445831],"iteration":292,"passed_time":0.163037539,"remaining_time":0.3934045735},
{"learn":[4.45692492],"iteration":293,"passed_time":0.1633827033,"remaining_time":0.3923407774},
{"learn":[4.454031688],"iteration":294,"passed_time":0.1637081178,"remaining_time":0.3912346544},
{"learn":[4.451672391],"iteration":295,"passed_time":0.1641148651,"remaining_time":0.3903272467},
{"learn":[4.45031553],"iteration":296,"passed_time":0.1643666134,"remaining_time":0.3890563274},
{"learn":[4.446782666],"iteration":297,"passed_time":0.1645875286,"remaining_time":0.3877196144},
{"learn":[4.444369689],"iteration":298,"passed_time":0.1649326513,"remaining_time":0.3866815672},
{"learn":[4.44411683],"iteration":299,"passed_time":0.165288149,"remaining_time":0.3856723476},
{"learn":[4.440876943],"iteration":300,"passed_time":0.1656060635,"remaining_time":0.384580194},
{"learn":[4.439336453],"iteration":301,"passed_time":0.1660014359,"remaining_time":0.3836721929},
{"learn":[4.436666901],"iteration":302,"passed_time":0.1663211837,"remaining_time":0.3825936141},
{"learn":[4.433043336],"iteration":303,"passed_time":0.1666042652,"remaining_time":0.3814360808},
{"learn":[4.431419305],"iteration":304,"passed_time":0.166832847,"remaining_time":0.380160094},
{"learn":[4.428859646],"iteration":305,"passed_time":0.1670740121,"remaining_time":0.3789194914},
{"learn":[4.424552441],"iteration":306,"passed_time":0.1673288854,"remaining_time":0.3777163438},
{"learn":[4.422706391],"iteration":307,"passed_time":0.1676228417,"remaining_time":0.3766071639},
{"learn":[4.421427994],"iteration":308,"passed_time":0.1678621318,"remaining_time":0.3753810132},
{"learn":[4.418733158],"iteration":309,"passed_time":0.1681588798,"remaining_time":0.3742891196},
{"learn":[4.415656941],"iteration":310,"passed_time":0.1685992936,"remaining_time":0.3735206214},
{"learn":[4.410747417],"iteration":311,"passed_time":0.1689545829,"remaining_time":0.3725665161},
{"learn":[4.408126521],"iteration":312,"passed_time":0.1692762891,"remaining_time":0.3715425258},
{"learn":[4.407843853],"iteration":313,"passed_time":0.1696642031,"remaining_time":0.370667654},
{"learn":[4.405219398],"iteration":314,"passed_time":0.1701010752,"remaining_time":0.3699023382},
{"learn":[4.402708465],"iteration":315,"passed_time":0.1706663215,"remaining_time":0.3694169743},
{"learn":[4.40104971],"iteration":316,"passed_time":0.1711184435,"remaining_time":0.3686873719},
{"learn":[4.400830038],"iteration":317,"passed_time":0.1716340234,"remaining_time":0.3680956098},
{"learn":[4.39784288],"iteration":318,"passed_time":0.1720103125,"remaining_time":0.3672069681},
{"learn":[4.393741845],"iteration":319,"passed_time":0.1724045599,"remaining_time":0.3663596898},
{"learn":[4.393425936],"iteration":320,"passed_time":0.1727064745,"remaining_time":0.3653199259},
{"learn":[4.390505974],"iteration":321,"passed_time":0.1730678888,"remaining_time":0.3644100267},
{"learn":[4.390305136],"iteration":322,"passed_time":0.1733640952,"remaining_time":0.3633668496},
{"learn":[4.38568203],"iteration":323,"passed_time":0.1736450516,"remaining_time":0.3622964657},
{"learn":[4.383057135],"iteration":324,"passed_time":0.1739723411,"remaining_time":0.36132717},
{"learn":[4.380662684],"iteration":325,"passed_time":0.1744015049,"remaining_time":0.3605724366},
{"learn":[4.37805727],"iteration":326,"passed_time":0.1747292527,"remaining_time":0.3596109697},
{"learn":[4.373708319],"iteration":327,"passed_time":0.1750561256,"remaining_time":0.3586515743},
{"learn":[4.36887921],"iteration":328,"passed_time":0.175439873,"remaining_time":0.3578120206},
{"learn":[4.367895929],"iteration":329,"passed_time":0.1757542876,"remaining_time":0.3568344627},
{"learn":[4.362140573],"iteration":330,"passed_time":0.1761130769,"remaining_time":0.3559505994},
{"learn":[4.361931924],"iteration":331,"passed_time":0.1764691995,"remaining_time":0.3550645339},
{"learn":[4.359656377],"iteration":332,"passed_time":0.1767884057,"remaining_time":0.3541077075},
{"learn":[4.354281355],"iteration":333,"passed_time":0.17713932,"remaining_time":0.3532179255},
{"learn":[4.348589447],"iteration":334,"passed_time":0.1774640262,"remaining_time":0.3522793356},
{"learn":[4.346355698],"iteration":335,"passed_time":0.177785274,"remaining_time":0.3513375654},
{"learn":[4.343894047],"iteration":336,"passed_time":0.1781207301,"remaining_time":0.3504274305},
{"learn":[4.341561356],"iteration":337,"passed_time":0.1785083942,"remaining_time":0.3496229496},
{"learn":[4.338869061],"iteration":338,"passed_time":0.1788934333,"remaining_time":0.3488158095},
{"learn":[4.333720063],"iteration":339,"passed_time":0.1792261394,"remaining_time":0.3479095648},
{"learn":[4.330892223],"iteration":340,"passed_time":0.179540554,"remaining_time":0.3469713346},
{"learn":[4.328311474],"iteration":341,"passed_time":0.1799576762,"remaining_time":0.3462343596},
{"learn":[4.324580133],"iteration":342,"passed_time":0.1803585486,"remaining_time":0.3454681236},
{"learn":[4.323354432],"iteration":343,"passed_time":0.1806685048,"remaining_time":0.3445306371},
{"learn":[4.323159553],"iteration":344,"passed_time":0.1810317108,"remaining_time":0.3436978856},
{"learn":[4.318639682],"iteration":345,"passed_time":0.1814099582,"remaining_time":0.3428962794},
{"learn":[4.312712208],"iteration":346,"passed_time":0.1817486643,"remaining_time":0.3420227026},
{"learn":[4.311461062],"iteration":347,"passed_time":0.1820715788,"remaining_time":0.3411226132},
{"learn":[4.311178356],"iteration":348,"passed_time":0.1824326598,"remaining_time":0.3402970244},
{"learn":[4.311102505],"iteration":349,"passed_time":0.1828161989,"remaining_time":0.3395157979},
{"learn":[4.310232308],"iteration":350,"passed_time":0.1831654049,"remaining_time":0.3386733554},
{"learn":[4.305128197],"iteration":351,"passed_time":0.183494486,"remaining_time":0.3377966674},
{"learn":[4.304595496],"iteration":352,"passed_time":0.1838257755,"remaining_time":0.3369271296},
{"learn":[4.3004992],"iteration":353,"passed_time":0.1841704398,"remaining_time":0.3360850399},
{"learn":[4.297581524],"iteration":354,"passed_time":0.184501646,"remaining_time":0.3352213004},
{"learn":[4.297355825],"iteration":355,"passed_time":0.184850602,"remaining_time":0.334392662},
{"learn":[4.295758715],"iteration":356,"passed_time":0.1851176419,"remaining_time":0.3334191701},
{"learn":[4.292500657],"iteration":357,"passed_time":0.1854628062,"remaining_time":0.3325897252},
{"learn":[4.290797586],"iteration":358,"passed_time":0.1858130539,"remaining_time":0.3317720545},
{"learn":[4.286410608],"iteration":359,"passed_time":0.1861659682,"remaining_time":0.3309617213},
{"learn":[4.280278245],"iteration":360,"passed_time":0.1865160076,"remaining_time":0.3301488333},
{"learn":[4.279941283],"iteration":361,"passed_time":0.186801964,"remaining_time":0.3292255608},
{"learn":[4.274426275],"iteration":362,"passed_time":0.1871205035,"remaining_time":0.3283629773},
{"learn":[4.273567658],"iteration":363,"passed_time":0.1874636679,"remaining_time":0.3275464088},
{"learn":[4.269488271],"iteration":364,"passed_time":0.187798374,"remaining_time":0.3267177192},
{"learn":[4.266838205],"iteration":365,"passed_time":0.1881785381,"remaining_time":0.3259704732},
{"learn":[4.263456509],"iteration":366,"passed_time":0.1892504893,"remaining_time":0.3264184189},
{"learn":[4.260360204],"iteration":367,"passed_time":0.1895407374,"remaining_time":0.3255156142},
{"learn":[4.255120549],"iteration":368,"passed_time":0.1898965267,"remaining_time":0.3247282069},
{"learn":[4.252582211],"iteration":369,"passed_time":0.1902547743,"remaining_time":0.3239473184},
{"learn":[4.247857931],"iteration":370,"passed_time":0.1914370164,"remaining_time":0.3245657233},
{"learn":[4.245288911],"iteration":371,"passed_time":0.1917700976,"remaining_time":0.3237409174},
{"learn":[4.24048515],"iteration":372,"passed_time":0.192096762,"remaining_time":0.3229079619},
{"learn":[4.2378365],"iteration":373,"passed_time":0.1931449634,"remaining_time":0.32328542},
{"learn":[4.236751063],"iteration":374,"passed_time":0.1935229609,"remaining_time":0.3225382681},
{"learn":[4.233240093],"iteration":375,"passed_time":0.1938461254,"remaining_time":0.3217020804},
{"learn":[4.230358421],"iteration":376,"passed_time":0.1941816648,"remaining_time":0.3208890642},
{"learn":[4.225853583],"iteration":377,"passed_time":0.1944837045,"remaining_time":0.3200234502},
{"learn":[4.224702126],"iteration":378,"passed_time":0.1948315355,"remaining_time":0.3192358405},
{"learn":[4.224361982],"iteration":379,"passed_time":0.1952049913,"remaining_time":0.3184923543},
{"learn":[4.223787954],"iteration":380,"passed_time":0.195650155,"remaining_time":0.3178673123},
{"learn":[4.22144054],"iteration":381,"passed_time":0.1960005277,"remaining_time":0.317089859},
{"learn":[4.217739335],"iteration":382,"passed_time":0.1963498587,"remaining_time":0.3163129578},
{"learn":[4.215611665],"iteration":383,"passed_time":0.1967225229,"remaining_time":0.3155757138},
{"learn":[4.210236863],"iteration":384,"passed_time":0.197103312,"remaining_time":0.3148533426},
{"learn":[4.208454294],"iteration":385,"passed_time":0.1974250599,"remaining_time":0.3140388258},
{"learn":[4.207446501],"iteration":386,"passed_time":0.1977695159,"remaining_time":0.313262825},
{"learn":[4.204985442],"iteration":387,"passed_time":0.198202638,"remaining_time":0.3126289033},
{"learn":[4.202796622],"iteration":388,"passed_time":0.1985438441,"remaining_time":0.311851642},
{"learn":[4.199774004],"iteration":389,"passed_time":0.1990241326,"remaining_time":0.3112941561},
{"learn":[4.199458358],"iteration":390,"passed_time":0.1994079217,"remaining_time":0.3105867629},
{"learn":[4.19751254],"iteration":391,"passed_time":0.1998182523,"remaining_time":0.3099221872},
{"learn":[4.195201346],"iteration":392,"passed_time":0.2001350418,"remaining_time":0.3091144285},
{"learn":[4.190593508],"iteration":393,"passed_time":0.2004923728,"remaining_time":0.3083715175},
{"learn":[4.187212054],"iteration":394,"passed_time":0.200756871,"remaining_time":0.3074883721},
{"learn":[4.184984466],"iteration":395,"passed_time":0.2011058687,"remaining_time":0.3067372341},
{"learn":[4.182832144],"iteration":396,"passed_time":0.201558574,"remaining_time":0.3061456427},
{"learn":[4.179752812],"iteration":397,"passed_time":0.2019575714,"remaining_time":0.3054735125},
{"learn":[4.17878934],"iteration":398,"passed_time":0.2024027767,"remaining_time":0.3048723529},
{"learn":[4.174548229],"iteration":399,"passed_time":0.2027349412,"remaining_time":0.3041024118},
{"learn":[4.168872556],"iteration":400,"passed_time":0.203059189,"remaining_time":0.3033228285},
{"learn":[4.163926494],"iteration":401,"passed_time":0.2033889785,"remaining_time":0.3025537541},
{"learn":[4.159485076],"iteration":402,"passed_time":0.2037192263,"remaining_time":0.3017875387},
{"learn":[4.155926102],"iteration":403,"passed_time":0.2040879738,"remaining_time":0.3010802782},
{"learn":[4.153540115],"iteration":404,"passed_time":0.204414805,"remaining_time":0.3003131086},
{"learn":[4.150983044],"iteration":405,"passed_time":0.2047109697,"remaining_time":0.2995032414},
{"learn":[4.146539132],"iteration":406,"passed_time":0.2050235093,"remaining_time":0.2987197567},
{"learn":[4.144869174],"iteration":407,"passed_time":0.2053810902,"remaining_time":0.2980039348},
{"learn":[4.142825962],"iteration":408,"passed_time":0.2058028791,"remaining_time":0.2973826443},
{"learn":[4.142467378],"iteration":409,"passed_time":0.2061177936,"remaining_time":0.2966085323},
{"learn":[4.141800768],"iteration":410,"passed_time":0.2064790829,"remaining_time":0.2959031139},
{"learn":[4.140107084],"iteration":411,"passed_time":0.2067879975,"remaining_time":0.2951246178},
{"learn":[4.136243196],"iteration":412,"passed_time":0.2071567451,"remaining_time":0.2944334367},
{"learn":[4.133618439],"iteration":413,"passed_time":0.2075376592,"remaining_time":0.2937610345},
{"learn":[4.131053025],"iteration":414,"passed_time":0.2078683653,"remaining_time":0.293019262},
{"learn":[4.128379975],"iteration":415,"passed_time":0.2082110714,"remaining_time":0.2922963117},
{"learn":[4.127068571],"iteration":416,"passed_time":0.2086051937,"remaining_time":0.2916470694},
{"learn":[4.125969877],"iteration":417,"passed_time":0.208965233,"remaining_time":0.2909515924},
{"learn":[4.123893633],"iteration":418,"passed_time":0.209362397,"remaining_time":0.2903091949},
{"learn":[4.119643722],"iteration":419,"passed_time":0.2097924358,"remaining_time":0.2897133638},
{"learn":[4.11465686],"iteration":420,"passed_time":0.2101785166,"remaining_time":0.2890578649},
{"learn":[4.111565986],"iteration":421,"passed_time":0.2105938055,"remaining_time":0.2884436483},
{"learn":[4.106322452],"iteration":422,"passed_time":0.2109192617,"remaining_time":0.2877078345},
{"learn":[4.104222175],"iteration":423,"passed_time":0.2113162174,"remaining_time":0.2870710877},
{"learn":[4.103008002],"iteration":424,"passed_time":0.2116820899,"remaining_time":0.2863934158},
{"learn":[4.099176337],"iteration":425,"passed_time":0.2120345042,"remaining_time":0.2856990738},
{"learn":[4.096525716],"iteration":426,"passed_time":0.2123208773,"remaining_time":0.2849177113},
{"learn":[4.094967724],"iteration":427,"passed_time":0.2127060831,"remaining_time":0.2842707466},
{"learn":[4.094683584],"iteration":428,"passed_time":0.2130545808,"remaining_time":0.2835761436},
{"learn":[4.091096563],"iteration":429,"passed_time":0.2134133284,"remaining_time":0.2828967376},
{"learn":[4.089178677],"iteration":430,"passed_time":0.2137822426,"remaining_time":0.2822322414},
{"learn":[4.085335077],"iteration":431,"passed_time":0.2141330319,"remaining_time":0.2815452827},
{"learn":[4.084852122],"iteration":432,"passed_time":0.2145132794,"remaining_time":0.2808984513},
{"learn":[4.080322952],"iteration":433,"passed_time":0.2148676937,"remaining_time":0.2802191581},
{"learn":[4.077449519],"iteration":434,"passed_time":0.2152948992,"remaining_time":0.2796359035},
{"learn":[4.076568374],"iteration":435,"passed_time":0.2156171887,"remaining_time":0.2789176478},
{"learn":[4.076071793],"iteration":436,"passed_time":0.2159703947,"remaining_time":0.2782410348},
{"learn":[4.075027644],"iteration":437,"passed_time":0.2164086001,"remaining_time":0.2776749618},
{"learn":[4.07020837],"iteration":438,"passed_time":0.2167775143,"remaining_time":0.2770209237},
{"learn":[4.06833694],"iteration":439,"passed_time":0.2171651367,"remaining_time":0.2763919922},
{"learn":[4.063936568],"iteration":440,"passed_time":0.2174950929,"remaining_time":0.2756910587},
{"learn":[4.061734926],"iteration":441,"passed_time":0.2179255483,"remaining_time":0.2751186787},
{"learn":[4.060815619],"iteration":442,"passed_time":0.2183245457,"remaining_time":0.2745073859},
{"learn":[4.056407489],"iteration":443,"passed_time":0.2186764183,"remaining_time":0.2738380374},
{"learn":[4.05238936],"iteration":444,"passed_time":0.2190162494,"remaining_time":0.2731550976},
{"learn":[4.049685254],"iteration":445,"passed_time":0.2194371216,"remaining_time":0.2725743618},
{"learn":[4.045162016],"iteration":446,"passed_time":0.2198497438,"remaining_time":0.271984135},
{"learn":[4.042955482],"iteration":447,"passed_time":0.2201688667,"remaining_time":0.2712794965},
{"learn":[4.041467663],"iteration":448,"passed_time":0.2204560731,"remaining_time":0.2705374082},
{"learn":[4.038920476],"iteration":449,"passed_time":0.2208054875,"remaining_time":0.2698733736},
{"learn":[4.036694383],"iteration":450,"passed_time":0.221169985,"remaining_time":0.2692290949},
{"learn":[4.034999007],"iteration":451,"passed_time":0.2215104411,"remaining_time":0.2685569065},
{"learn":[4.031928018],"iteration":452,"passed_time":0.2224531015,"remaining_time":0.2686133477},
{"learn":[4.028718143],"iteration":453,"passed_time":0.2235057612,"remaining_time":0.2687976775},
{"learn":[4.027401978],"iteration":454,"passed_time":0.2238205507,"remaining_time":0.2680927476},
{"learn":[4.025930598],"iteration":455,"passed_time":0.2242527562,"remaining_time":0.2675296039},
{"learn":[4.021074523],"iteration":456,"passed_time":0.2245584208,"remaining_time":0.2668166794},
{"learn":[4.020268486],"iteration":457,"passed_time":0.224882627,"remaining_time":0.2661274756},
{"learn":[4.017986361],"iteration":458,"passed_time":0.225226708,"remaining_time":0.2654632877},
{"learn":[4.014814804],"iteration":459,"passed_time":0.2255878306,"remaining_time":0.2648204968},
{"learn":[4.009704796],"iteration":460,"passed_time":0.2259167451,"remaining_time":0.2641412703},
{"learn":[4.008440457],"iteration":461,"passed_time":0.2263298673,"remaining_time":0.2635616204},
{"learn":[4.004854849],"iteration":462,"passed_time":0.2266040738,"remaining_time":0.2628215716},
{"learn":[4.000898028],"iteration":463,"passed_time":0.2270186128,"remaining_time":0.2622456389},
{"learn":[3.996617985],"iteration":464,"passed_time":0.2273518605,"remaining_time":0.2615768718},
{"learn":[3.995443319],"iteration":465,"passed_time":0.227724733,"remaining_time":0.2609549516},
{"learn":[3.990771995],"iteration":466,"passed_time":0.2280445226,"remaining_time":0.2602735129},
{"learn":[3.989249359],"iteration":467,"passed_time":0.2284673531,"remaining_time":0.2597107518},
{"learn":[3.986599538],"iteration":468,"passed_time":0.2287756844,"remaining_time":0.2590189518},
{"learn":[3.985628919],"iteration":469,"passed_time":0.2291496819,"remaining_time":0.2584028328},
{"learn":[3.985086112],"iteration":470,"passed_time":0.2294893463,"remaining_time":0.2577491809},
{"learn":[3.98466839],"iteration":471,"passed_time":0.2298560939,"remaining_time":0.2571271558},
{"learn":[3.984233894],"iteration":472,"passed_time":0.2301712584,"remaining_time":0.2564487382},
{"learn":[3.981855845],"iteration":473,"passed_time":0.2305248394,"remaining_time":0.2558144842},
{"learn":[3.978684264],"iteration":474,"passed_time":0.2308865037,"remaining_time":0.2551903461},
{"learn":[3.974361269],"iteration":475,"passed_time":0.2312327097,"remaining_time":0.2545502939},
{"learn":[3.972074049],"iteration":476,"passed_time":0.2315815824,"remaining_time":0.2539143974},
{"learn":[3.97191982],"iteration":477,"passed_time":0.2319236217,"remaining_time":0.2532722396},
{"learn":[3.969616848],"iteration":478,"passed_time":0.2330455309,"remaining_time":0.2534795858},
{"learn":[3.968533527],"iteration":479,"passed_time":0.2334483199,"remaining_time":0.2529023466},
{"learn":[3.967568753],"iteration":480,"passed_time":0.2337966926,"remaining_time":0.2522671174},
{"learn":[3.966232553],"iteration":481,"passed_time":0.2341792317,"remaining_time":0.2516697967},
{"learn":[3.961522393],"iteration":482,"passed_time":0.2345311044,"remaining_time":0.2510405403},
{"learn":[3.955829553],"iteration":483,"passed_time":0.2348570605,"remaining_time":0.2503848001},
{"learn":[3.954248095],"iteration":484,"passed_time":0.2351423503,"remaining_time":0.249687238},
{"learn":[3.951922606],"iteration":485,"passed_time":0.2355537226,"remaining_time":0.2491247189},
{"learn":[3.94978202],"iteration":486,"passed_time":0.235889262,"remaining_time":0.2484829392},
{"learn":[3.949518999],"iteration":487,"passed_time":0.2362832177,"remaining_time":0.2479037038},
{"learn":[3.945431216],"iteration":488,"passed_time":0.2366595902,"remaining_time":0.2473068519},
{"learn":[3.943249086],"iteration":489,"passed_time":0.2370175878,"remaining_time":0.2466917751},
{"learn":[3.941981548],"iteration":490,"passed_time":0.2373385023,"remaining_time":0.2460393028},
{"learn":[3.936600517],"iteration":491,"passed_time":0.2377179165,"remaining_time":0.2454485804},
{"learn":[3.934476885],"iteration":492,"passed_time":0.2380829974,"remaining_time":0.244843975},
{"learn":[3.93045798],"iteration":493,"passed_time":0.2384170785,"remaining_time":0.2442085865},
{"learn":[3.925977375],"iteration":494,"passed_time":0.2387548679,"remaining_time":0.2435781986},
{"learn":[3.92457993],"iteration":495,"passed_time":0.2391446153,"remaining_time":0.2430017865},
{"learn":[3.919849146],"iteration":496,"passed_time":0.2395145712,"remaining_time":0.2424060952},
{"learn":[3.919681964],"iteration":497,"passed_time":0.2399050269,"remaining_time":0.2418319749},
{"learn":[3.917633027],"iteration":498,"passed_time":0.2403227325,"remaining_time":0.2412859498},
{"learn":[3.916616419],"iteration":499,"passed_time":0.240743688,"remaining_time":0.240743688},
{"learn":[3.912896166],"iteration":500,"passed_time":0.2410906857,"remaining_time":0.2401282478},
{"learn":[3.912769674],"iteration":501,"passed_time":0.2414563916,"remaining_time":0.2395324363},
{"learn":[3.909373788],"iteration":502,"passed_time":0.2418139309,"remaining_time":0.2389294705},
{"learn":[3.906706036],"iteration":503,"passed_time":0.2421429287,"remaining_time":0.2382993901},
{"learn":[3.903895664],"iteration":504,"passed_time":0.2425528843,"remaining_time":0.2377498569},
{"learn":[3.902982967],"iteration":505,"passed_time":0.2428806738,"remaining_time":0.2371206578},
{"learn":[3.900905528],"iteration":506,"passed_time":0.2432741295,"remaining_time":0.2365565006},
{"learn":[3.897463465],"iteration":507,"passed_time":0.2435582109,"remaining_time":0.2358870862},
{"learn":[3.895918033],"iteration":508,"passed_time":0.2438700005,"remaining_time":0.235245914},
{"learn":[3.893921936],"iteration":509,"passed_time":0.2442602479,"remaining_time":0.2346814146},
{"learn":[3.890237934],"iteration":510,"passed_time":0.2445798708,"remaining_time":0.2340500133},
{"learn":[3.887311613],"iteration":511,"passed_time":0.2449711598,"remaining_time":0.2334881367},
{"learn":[3.884869735],"iteration":512,"passed_time":0.2453561989,"remaining_time":0.232920992},
{"learn":[3.882101231],"iteration":513,"passed_time":0.2456867384,"remaining_time":0.232303025},
{"learn":[3.88060368],"iteration":514,"passed_time":0.2460547776,"remaining_time":0.2317214896},
{"learn":[3.877726076],"iteration":515,"passed_time":0.2463987753,"remaining_time":0.2311182311},
{"learn":[3.874938145],"iteration":516,"passed_time":0.2468231058,"remaining_time":0.2305910254},
{"learn":[3.874340833],"iteration":517,"passed_time":0.2472091449,"remaining_time":0.2300285866},
{"learn":[3.873105224],"iteration":518,"passed_time":0.2476123089,"remaining_time":0.2294826986},
{"learn":[3.869800236],"iteration":519,"passed_time":0.2479975147,"remaining_time":0.2289207828},
{"learn":[3.867932518],"iteration":520,"passed_time":0.2482773045,"remaining_time":0.2282626273},
{"learn":[3.866666962],"iteration":521,"passed_time":0.2486516353,"remaining_time":0.2276924936},
{"learn":[3.865527652],"iteration":522,"passed_time":0.2490345078,"remaining_time":0.2271308991},
{"learn":[3.861900081],"iteration":523,"passed_time":0.2494175052,"remaining_time":0.2265701002},
{"learn":[3.858502887],"iteration":524,"passed_time":0.2498071693,"remaining_time":0.2260160103},
{"learn":[3.858335097],"iteration":525,"passed_time":0.2502073333,"remaining_time":0.2254720076},
{"learn":[3.855719306],"iteration":526,"passed_time":0.2505313728,"remaining_time":0.2248602264},
{"learn":[3.855137428],"iteration":527,"passed_time":0.2508389957,"remaining_time":0.2242348598},
{"learn":[3.851985706],"iteration":528,"passed_time":0.2511812018,"remaining_time":0.2236414859},
{"learn":[3.851051809],"iteration":529,"passed_time":0.2515319911,"remaining_time":0.2230566714},
{"learn":[3.850679146],"iteration":530,"passed_time":0.2519418634,"remaining_time":0.2225249227},
{"learn":[3.848179484],"iteration":531,"passed_time":0.2523086526,"remaining_time":0.221955732},
{"learn":[3.844551071],"iteration":532,"passed_time":0.2526342338,"remaining_time":0.2213511955},
{"learn":[3.841604794],"iteration":533,"passed_time":0.2529761898,"remaining_time":0.2207619934},
{"learn":[3.83969656],"iteration":534,"passed_time":0.2533750622,"remaining_time":0.2202231849},
{"learn":[3.836811463],"iteration":535,"passed_time":0.2537382264,"remaining_time":0.2196539871},
{"learn":[3.834182551],"iteration":536,"passed_time":0.2540705159,"remaining_time":0.2190589364},
{"learn":[3.828012842],"iteration":537,"passed_time":0.2544493884,"remaining_time":0.2185048651},
{"learn":[3.826636176],"iteration":538,"passed_time":0.2547475114,"remaining_time":0.2178823799},
{"learn":[3.826189798],"iteration":539,"passed_time":0.2551153006,"remaining_time":0.2173204412},
{"learn":[3.824104738],"iteration":540,"passed_time":0.2554185486,"remaining_time":0.2167044617},
{"learn":[3.82300218],"iteration":541,"passed_time":0.2557660046,"remaining_time":0.2161269928},
{"learn":[3.817146402],"iteration":542,"passed_time":0.2561220856,"remaining_time":0.21555763},
{"learn":[3.814638044],"iteration":543,"passed_time":0.2564694582,"remaining_time":0.2149817518},
{"learn":[3.812979573],"iteration":544,"passed_time":0.2568342058,"remaining_time":0.2144212177},
{"learn":[3.811938825],"iteration":545,"passed_time":0.257209745,"remaining_time":0.213870374},
{"learn":[3.811479418],"iteration":546,"passed_time":0.257611159,"remaining_time":0.2133415997},
{"learn":[3.80742981],"iteration":547,"passed_time":0.2579443234,"remaining_time":0.2127569967},
{"learn":[3.805097043],"iteration":548,"passed_time":0.2582362381,"remaining_time":0.2121394233},
{"learn":[3.801577232],"iteration":549,"passed_time":0.2586027774,"remaining_time":0.2115840906},
{"learn":[3.799762083],"iteration":550,"passed_time":0.2589363168,"remaining_time":0.2110025522},
{"learn":[3.796393455],"iteration":551,"passed_time":0.2592910644,"remaining_time":0.2104391248},
{"learn":[3.793486459],"iteration":552,"passed_time":0.2596591453,"remaining_time":0.2098872296},
{"learn":[3.792006091],"iteration":553,"passed_time":0.2600331012,"remaining_time":0.2093407277},
{"learn":[3.78932128],"iteration":554,"passed_time":0.2603991404,"remaining_time":0.2087885},
{"learn":[3.787581812],"iteration":555,"passed_time":0.2607363048,"remaining_time":0.2082138837},
{"learn":[3.785308865],"iteration":556,"passed_time":0.2612222182,"remaining_time":0.2077584249},
{"learn":[3.78465475],"iteration":557,"passed_time":0.261566341,"remaining_time":0.2071905425},
{"learn":[3.780498869],"iteration":558,"passed_time":0.2618927971,"remaining_time":0.2066095233},
{"learn":[3.778734909],"iteration":559,"passed_time":0.2622629196,"remaining_time":0.2060637226},
{"learn":[3.778652349],"iteration":560,"passed_time":0.2626703336,"remaining_time":0.2055477299},
{"learn":[3.777928006],"iteration":561,"passed_time":0.2629922481,"remaining_time":0.2049654887},
{"learn":[3.776131406],"iteration":562,"passed_time":0.2633871622,"remaining_time":0.2044408346},
{"learn":[3.772925617],"iteration":563,"passed_time":0.2636844935,"remaining_time":0.2038412042},
{"learn":[3.7727745],"iteration":564,"passed_time":0.264003908,"remaining_time":0.203259646},
{"learn":[3.771763073],"iteration":565,"passed_time":0.2643733223,"remaining_time":0.2027173531},
{"learn":[3.768738162],"iteration":566,"passed_time":0.2647322365,"remaining_time":0.2021676515},
{"learn":[3.767220794],"iteration":567,"passed_time":0.2650247346,"remaining_time":0.201568108},
{"learn":[3.766691102],"iteration":568,"passed_time":0.2653920238,"remaining_time":0.2010262957},
{"learn":[3.766259335],"iteration":569,"passed_time":0.2657652296,"remaining_time":0.2004895592},
{"learn":[3.76116362],"iteration":570,"passed_time":0.2661413105,"remaining_time":0.1999555555},
{"learn":[3.758633056],"iteration":571,"passed_time":0.2665911408,"remaining_time":0.1994772872},
{"learn":[3.754603809],"iteration":572,"passed_time":0.2669459301,"remaining_time":0.1989282935},
{"learn":[3.754070549],"iteration":573,"passed_time":0.2673298442,"remaining_time":0.1984015917},
{"learn":[3.750534319],"iteration":574,"passed_time":0.2677247166,"remaining_time":0.1978834862},
{"learn":[3.746491516],"iteration":575,"passed_time":0.2681017974,"remaining_time":0.197352712},
{"learn":[3.744210544],"iteration":576,"passed_time":0.2684195036,"remaining_time":0.1967789429},
{"learn":[3.742929991],"iteration":577,"passed_time":0.268768043,"remaining_time":0.1962285712},
{"learn":[3.740402992],"iteration":578,"passed_time":0.2690977908,"remaining_time":0.195665233},
{"learn":[3.739644243],"iteration":579,"passed_time":0.2694529134,"remaining_time":0.1951210752},
{"learn":[3.737529404],"iteration":580,"passed_time":0.2697761613,"remaining_time":0.194554581},
{"learn":[3.737196923],"iteration":581,"passed_time":0.2702268666,"remaining_time":0.1940804643},
{"learn":[3.733954464],"iteration":582,"passed_time":0.2705766559,"remaining_time":0.1935342462},
{"learn":[3.731608623],"iteration":583,"passed_time":0.2709803199,"remaining_time":0.1930270772},
{"learn":[3.729843952],"iteration":584,"passed_time":0.2713271509,"remaining_time":0.1924799447},
{"learn":[3.727223798],"iteration":585,"passed_time":0.2716698153,"remaining_time":0.1919305521},
{"learn":[3.725351667],"iteration":586,"passed_time":0.2719937298,"remaining_time":0.1913686719},
{"learn":[3.725026912],"iteration":587,"passed_time":0.272410352,"remaining_time":0.1908725596},
{"learn":[3.721974565],"iteration":588,"passed_time":0.2727833496,"remaining_time":0.1903462762},
{"learn":[3.720269493],"iteration":589,"passed_time":0.2731616387,"remaining_time":0.1898241896},
{"learn":[3.718907466],"iteration":590,"passed_time":0.2735744693,"remaining_time":0.189326494},
{"learn":[3.715602912],"iteration":591,"passed_time":0.2739881332,"remaining_time":0.1888296594},
{"learn":[3.714463059],"iteration":592,"passed_time":0.2742998395,"remaining_time":0.1882631276},
{"learn":[3.710802077],"iteration":593,"passed_time":0.274662962,"remaining_time":0.187732597},
{"learn":[3.708032435],"iteration":594,"passed_time":0.2750272513,"remaining_time":0.1872034231},
{"learn":[3.703788939],"iteration":595,"passed_time":0.2754169987,"remaining_time":0.1866920595},
{"learn":[3.702500944],"iteration":596,"passed_time":0.2757920795,"remaining_time":0.1861712028},
{"learn":[3.698196925],"iteration":597,"passed_time":0.2761979518,"remaining_time":0.1856715328},
{"learn":[3.69658891],"iteration":598,"passed_time":0.2765591161,"remaining_time":0.1851422463},
{"learn":[3.696124066],"iteration":599,"passed_time":0.2769096554,"remaining_time":0.1846064369},
{"learn":[3.693537052],"iteration":600,"passed_time":0.2772403615,"remaining_time":0.184058077},
{"learn":[3.691343275],"iteration":601,"passed_time":0.2775778176,"remaining_time":0.1835149027},
{"learn":[3.690973831],"iteration":602,"passed_time":0.2779344819,"remaining_time":0.1829850569},
{"learn":[3.686151073],"iteration":603,"passed_time":0.278265813,"remaining_time":0.1824391754},
{"learn":[3.683921982],"iteration":604,"passed_time":0.2786265606,"remaining_time":0.181913209},
{"learn":[3.679975271],"iteration":605,"passed_time":0.2789765166,"remaining_time":0.1813807715},
{"learn":[3.674047638],"iteration":606,"passed_time":0.2793303893,"remaining_time":0.1808514712},
{"learn":[3.673151794],"iteration":607,"passed_time":0.2797173034,"remaining_time":0.1803440509},
{"learn":[3.670953108],"iteration":608,"passed_time":0.2801373006,"remaining_time":0.1798582669},
{"learn":[3.6703947],"iteration":609,"passed_time":0.2804823816,"remaining_time":0.1793248014},
{"learn":[3.668433805],"iteration":610,"passed_time":0.2807786713,"remaining_time":0.1787608889},
{"learn":[3.668304956],"iteration":611,"passed_time":0.2812059185,"remaining_time":0.1782808764},
{"learn":[3.667880012],"iteration":612,"passed_time":0.2816623738,"remaining_time":0.1778194758},
{"learn":[3.667282264],"iteration":613,"passed_time":0.2820362046,"remaining_time":0.1773061482},
{"learn":[3.664611483],"iteration":614,"passed_time":0.2823976605,"remaining_time":0.1767855273},
{"learn":[3.662543394],"iteration":615,"passed_time":0.2826821586,"remaining_time":0.1762174495},
{"learn":[3.659041959],"iteration":616,"passed_time":0.2830834476,"remaining_time":0.1757227884},
{"learn":[3.656868545],"iteration":617,"passed_time":0.2834182787,"remaining_time":0.1751873503},
{"learn":[3.654785614],"iteration":618,"passed_time":0.2838294426,"remaining_time":0.1746995439},
{"learn":[3.654566096],"iteration":619,"passed_time":0.2842424816,"remaining_time":0.1742131339},
{"learn":[3.651007045],"iteration":620,"passed_time":0.284628229,"remaining_time":0.173710304},
{"learn":[3.648921786],"iteration":621,"passed_time":0.2850161431,"remaining_time":0.1732091673},
{"learn":[3.647655706],"iteration":622,"passed_time":0.2854121821,"remaining_time":0.1727133108},
{"learn":[3.647241144],"iteration":623,"passed_time":0.2858275543,"remaining_time":0.1722294238},
{"learn":[3.644195689],"iteration":624,"passed_time":0.2861691771,"remaining_time":0.1717015062},
{"learn":[3.642632246],"iteration":625,"passed_time":0.2865406746,"remaining_time":0.1711920324},
{"learn":[3.642523322],"iteration":626,"passed_time":0.2868070478,"remaining_time":0.1706204607},
{"learn":[3.641494659],"iteration":627,"passed_time":0.2872241284,"remaining_time":0.1701391334},
{"learn":[3.63976496],"iteration":628,"passed_time":0.2875805843,"remaining_time":0.1696222524},
{"learn":[3.637945652],"iteration":629,"passed_time":0.2879752067,"remaining_time":0.169128296},
{"learn":[3.636233667],"iteration":630,"passed_time":0.2883901206,"remaining_time":0.1686465206},
{"learn":[3.635304404],"iteration":631,"passed_time":0.2887711181,"remaining_time":0.168145208},
{"learn":[3.632234951],"iteration":632,"passed_time":0.2891304907,"remaining_time":0.1676317379},
{"learn":[3.631630987],"iteration":633,"passed_time":0.289534113,"remaining_time":0.1671442987},
{"learn":[3.630301009],"iteration":634,"passed_time":0.2898701524,"remaining_time":0.1666182766},
{"learn":[3.629077964],"iteration":635,"passed_time":0.2901995252,"remaining_time":0.1660890364},
{"learn":[3.628004522],"iteration":636,"passed_time":0.2905141898,"remaining_time":0.1655520422},
{"learn":[3.625062876],"iteration":637,"passed_time":0.2908963122,"remaining_time":0.1650540204},
{"learn":[3.624917986],"iteration":638,"passed_time":0.2912963096,"remaining_time":0.1645664597},
{"learn":[3.622887087],"iteration":639,"passed_time":0.291687807,"remaining_time":0.1640743914},
{"learn":[3.621220865],"iteration":640,"passed_time":0.2920748877,"remaining_time":0.1635801633},
{"learn":[3.621143844],"iteration":641,"passed_time":0.2924236771,"remaining_time":0.1630649165},
{"learn":[3.620822821],"iteration":642,"passed_time":0.2927896746,"remaining_time":0.1625597416},
{"learn":[3.619202826],"iteration":643,"passed_time":0.293135214,"remaining_time":0.1620436897},
{"learn":[3.618204882],"iteration":644,"passed_time":0.2934678368,"remaining_time":0.1615210575},
{"learn":[3.614259666],"iteration":645,"passed_time":0.2937599598,"remaining_time":0.1609768201},
{"learn":[3.613415661],"iteration":646,"passed_time":0.294088916,"remaining_time":0.160453458},
{"learn":[3.611096773],"iteration":647,"passed_time":0.2943837057,"remaining_time":0.1599121364},
{"learn":[3.610820695],"iteration":648,"passed_time":0.2947015786,"remaining_time":0.1593840587},
{"learn":[3.609290065],"iteration":649,"passed_time":0.2950887843,"remaining_time":0.1588939608},
{"learn":[3.60897947],"iteration":650,"passed_time":0.2953777824,"remaining_time":0.15835153},
{"learn":[3.606570702],"iteration":651,"passed_time":0.2956851137,"remaining_time":0.1578196619},
{"learn":[3.606292637],"iteration":652,"passed_time":0.2959725701,"remaining_time":0.1572779201},
{"learn":[3.602753838],"iteration":653,"passed_time":0.2963754007,"remaining_time":0.1567979949},
{"learn":[3.599755869],"iteration":654,"passed_time":0.296781398,"remaining_time":0.156319973},
{"learn":[3.599509575],"iteration":655,"passed_time":0.2971473123,"remaining_time":0.1558211516},
{"learn":[3.595337722],"iteration":656,"passed_time":0.2974664768,"remaining_time":0.1552983281},
{"learn":[3.595168561],"iteration":657,"passed_time":0.2978629325,"remaining_time":0.1548162962},
{"learn":[3.59290559],"iteration":658,"passed_time":0.2982326384,"remaining_time":0.1543206824},
{"learn":[3.592015928],"iteration":659,"passed_time":0.2985482613,"remaining_time":0.1537975891},
{"learn":[3.590680403],"iteration":660,"passed_time":0.2988626758,"remaining_time":0.1532745039},
{"learn":[3.590361532],"iteration":661,"passed_time":0.2991803821,"remaining_time":0.1527537298},
{"learn":[3.589069739],"iteration":662,"passed_time":0.2995305464,"remaining_time":0.1522500666},
{"learn":[3.585010186],"iteration":663,"passed_time":0.2998413777,"remaining_time":0.1517269622},
{"learn":[3.582997552],"iteration":664,"passed_time":0.3002055419,"remaining_time":0.1512313632},
{"learn":[3.582119256],"iteration":665,"passed_time":0.300583081,"remaining_time":0.1507428665},
{"learn":[3.579019356],"iteration":666,"passed_time":0.3009821201,"remaining_time":0.1502654363},
{"learn":[3.57719559],"iteration":667,"passed_time":0.3012798681,"remaining_time":0.1497378985},
{"learn":[3.574050046],"iteration":668,"passed_time":0.3016614905,"remaining_time":0.1492525461},
{"learn":[3.572204518],"iteration":669,"passed_time":0.3020176548,"remaining_time":0.1487549643},
{"learn":[3.569508025],"iteration":670,"passed_time":0.3023049446,"remaining_time":0.1482240339},
{"learn":[3.566268704],"iteration":671,"passed_time":0.3026306924,"remaining_time":0.1477125999},
{"learn":[3.562564052],"iteration":672,"passed_time":0.3029750651,"remaining_time":0.1472107672},
{"learn":[3.561173586],"iteration":673,"passed_time":0.3032469383,"remaining_time":0.1466743351},
{"learn":[3.559551904],"iteration":674,"passed_time":0.3035856027,"remaining_time":0.1461708458},
{"learn":[3.558593054],"iteration":675,"passed_time":0.3040137249,"remaining_time":0.1457107202},
{"learn":[3.555647008],"iteration":676,"passed_time":0.3043804308,"remaining_time":0.1452213872},
{"learn":[3.553100059],"iteration":677,"passed_time":0.304686137,"remaining_time":0.1447034456},
{"learn":[3.55085578],"iteration":678,"passed_time":0.3050598846,"remaining_time":0.1442182959},
{"learn":[3.550737965],"iteration":679,"passed_time":0.3054672568,"remaining_time":0.1437492973},
{"learn":[3.549408772],"iteration":680,"passed_time":0.3058527543,"remaining_time":0.1432702329},
{"learn":[3.547390589],"iteration":681,"passed_time":0.3061802104,"remaining_time":0.1427643796},
{"learn":[3.54723575],"iteration":682,"passed_time":0.3066257908,"remaining_time":0.1423138736},
{"learn":[3.543988891],"iteration":683,"passed_time":0.3069571636,"remaining_time":0.1418106194},
{"learn":[3.543868508],"iteration":684,"passed_time":0.3073177029,"remaining_time":0.1413212794},
{"learn":[3.542752124],"iteration":685,"passed_time":0.3076825754,"remaining_time":0.1408342984},
{"learn":[3.541334315],"iteration":686,"passed_time":0.3080554063,"remaining_time":0.1403512986},
{"learn":[3.540208266],"iteration":687,"passed_time":0.3084466537,"remaining_time":0.1398769708},
{"learn":[3.537730983],"iteration":688,"passed_time":0.308890359,"remaining_time":0.1394265626},
{"learn":[3.53419867],"iteration":689,"passed_time":0.3093604809,"remaining_time":0.1389880421},
{"learn":[3.532628335],"iteration":690,"passed_time":0.309645979,"remaining_time":0.1384668705},
{"learn":[3.532204987],"iteration":691,"passed_time":0.3099566436,"remaining_time":0.1379575813},
{"learn":[3.530618147],"iteration":692,"passed_time":0.3102490583,"remaining_time":0.1374407805},
{"learn":[3.528909306],"iteration":693,"passed_time":0.3105875977,"remaining_time":0.1369449638},
{"learn":[3.526700678],"iteration":694,"passed_time":0.3109921367,"remaining_time":0.1364785636},
{"learn":[3.526439574],"iteration":695,"passed_time":0.3113809258,"remaining_time":0.1360054618},
{"learn":[3.525784216],"iteration":696,"passed_time":0.3117214235,"remaining_time":0.1355116088},
{"learn":[3.524112693],"iteration":697,"passed_time":0.3120570463,"remaining_time":0.1350160859},
{"learn":[3.522813541],"iteration":698,"passed_time":0.3124257522,"remaining_time":0.1345352667},
{"learn":[3.519148203],"iteration":699,"passed_time":0.3127687915,"remaining_time":0.1340437678},
{"learn":[3.517236747],"iteration":700,"passed_time":0.3131222892,"remaining_time":0.1335571533},
{"learn":[3.515603888],"iteration":701,"passed_time":0.313451037,"remaining_time":0.1330604117},
{"learn":[3.51263524],"iteration":702,"passed_time":0.3138257845,"remaining_time":0.1325835818},
{"learn":[3.51123442],"iteration":703,"passed_time":0.3141906154,"remaining_time":0.1321028724},
{"learn":[3.50828027],"iteration":704,"passed_time":0.3145446964,"remaining_time":0.1316179935},
{"learn":[3.508265537],"iteration":705,"passed_time":0.3147029037,"remaining_time":0.1310519174},
{"learn":[3.506774876],"iteration":706,"passed_time":0.3150679012,"remaining_time":0.1305726946},
{"learn":[3.50552068],"iteration":707,"passed_time":0.3154090656,"remaining_time":0.1300839649},
{"learn":[3.501973993],"iteration":708,"passed_time":0.3158146046,"remaining_time":0.1296220733},
{"learn":[3.498880354],"iteration":709,"passed_time":0.3161232275,"remaining_time":0.1291207549},
{"learn":[3.497370959],"iteration":710,"passed_time":0.3163724342,"remaining_time":0.1285958277},
{"learn":[3.496050455],"iteration":711,"passed_time":0.3165983077,"remaining_time":0.1280622368},
{"learn":[3.495630067],"iteration":712,"passed_time":0.3168181812,"remaining_time":0.127527094},
{"learn":[3.49550669],"iteration":713,"passed_time":0.3170947627,"remaining_time":0.1270155492},
{"learn":[3.493652375],"iteration":714,"passed_time":0.3174150939,"remaining_time":0.1265221004},
{"learn":[3.491915684],"iteration":715,"passed_time":0.3177712582,"remaining_time":0.1260433482},
{"learn":[3.490303956],"iteration":716,"passed_time":0.3184167539,"remaining_time":0.1256791372},
{"learn":[3.488363853],"iteration":717,"passed_time":0.3186916688,"remaining_time":0.1251685941},
{"learn":[3.485483936],"iteration":718,"passed_time":0.3191015827,"remaining_time":0.1247114669},
{"learn":[3.483763466],"iteration":719,"passed_time":0.3195130799,"remaining_time":0.1242550866},
{"learn":[3.481642352],"iteration":720,"passed_time":0.3198919108,"remaining_time":0.1237861902},
{"learn":[3.479826119],"iteration":721,"passed_time":0.3202368251,"remaining_time":0.1233044839},
{"learn":[3.478588728],"iteration":722,"passed_time":0.3205782812,"remaining_time":0.1228218311},
{"learn":[3.475390887],"iteration":723,"passed_time":0.3208825708,"remaining_time":0.1223253999},
{"learn":[3.472636852],"iteration":724,"passed_time":0.3212174019,"remaining_time":0.1218410835},
{"learn":[3.47061883],"iteration":725,"passed_time":0.3215860661,"remaining_time":0.1213699478},
{"learn":[3.46953149],"iteration":726,"passed_time":0.3219007724,"remaining_time":0.120878832},
{"learn":[3.467217162],"iteration":727,"passed_time":0.3222653116,"remaining_time":0.1204068197},
{"learn":[3.465686216],"iteration":728,"passed_time":0.322614101,"remaining_time":0.1199292474},
{"learn":[3.462631216],"iteration":729,"passed_time":0.3229665153,"remaining_time":0.1194533687},
{"learn":[3.461451053],"iteration":730,"passed_time":0.3232788465,"remaining_time":0.1189630776},
{"learn":[3.458950469],"iteration":731,"passed_time":0.3235827612,"remaining_time":0.1184701912},
{"learn":[3.458072145],"iteration":732,"passed_time":0.3239005091,"remaining_time":0.1179828594},
{"learn":[3.454364268],"iteration":733,"passed_time":0.3252427084,"remaining_time":0.1178672486},
{"learn":[3.453243406],"iteration":734,"passed_time":0.325607956,"remaining_time":0.1173960658},
{"learn":[3.453017963],"iteration":735,"passed_time":0.3258851625,"remaining_time":0.1168935909},
{"learn":[3.45201581],"iteration":736,"passed_time":0.3263164096,"remaining_time":0.1164466971},
{"learn":[3.449510107],"iteration":737,"passed_time":0.3266792405,"remaining_time":0.1159755569},
{"learn":[3.447189189],"iteration":738,"passed_time":0.3269920718,"remaining_time":0.1154870511},
{"learn":[3.446423605],"iteration":739,"passed_time":0.3273532361,"remaining_time":0.1150160019},
{"learn":[3.445531987],"iteration":740,"passed_time":0.3277530251,"remaining_time":0.1145587496},
{"learn":[3.445328199],"iteration":741,"passed_time":0.3281053144,"remaining_time":0.1140851363},
{"learn":[3.443327544],"iteration":742,"passed_time":0.3283756876,"remaining_time":0.1135835151},
{"learn":[3.441475798],"iteration":743,"passed_time":0.3286830189,"remaining_time":0.1130952323},
{"learn":[3.439046501],"iteration":744,"passed_time":0.3290694746,"remaining_time":0.1126345182},
{"learn":[3.435899469],"iteration":745,"passed_time":0.3293990558,"remaining_time":0.1121546383},
{"learn":[3.433988352],"iteration":746,"passed_time":0.3297726366,"remaining_time":0.111690063},
{"learn":[3.433413263],"iteration":747,"passed_time":0.3300974678,"remaining_time":0.1112093073},
{"learn":[3.429944699],"iteration":748,"passed_time":0.3303974658,"remaining_time":0.1107206461},
{"learn":[3.429291634],"iteration":749,"passed_time":0.3307472968,"remaining_time":0.1102490989},
{"learn":[3.429175603],"iteration":750,"passed_time":0.3310695863,"remaining_time":0.1097687443},
{"learn":[3.428780323],"iteration":751,"passed_time":0.3313923758,"remaining_time":0.109288975},
{"learn":[3.423893341],"iteration":752,"passed_time":0.3317537484,"remaining_time":0.1088222787},
{"learn":[3.421024316],"iteration":753,"passed_time":0.3321285792,"remaining_time":0.1083602526},
{"learn":[3.420969872],"iteration":754,"passed_time":0.3324345355,"remaining_time":0.1078761076},
{"learn":[3.419544785],"iteration":755,"passed_time":0.3328132414,"remaining_time":0.1074159139},
{"learn":[3.417057977],"iteration":756,"passed_time":0.3332445301,"remaining_time":0.1069728148},
{"learn":[3.415160245],"iteration":757,"passed_time":0.3335866945,"remaining_time":0.106501293},
{"learn":[3.412854597],"iteration":758,"passed_time":0.3339884835,"remaining_time":0.1060490442},
{"learn":[3.410926347],"iteration":759,"passed_time":0.3343354395,"remaining_time":0.1055796125},
{"learn":[3.408963843],"iteration":760,"passed_time":0.3346369792,"remaining_time":0.1050962392},
{"learn":[3.407629634],"iteration":761,"passed_time":0.3349453105,"remaining_time":0.1046154644},
{"learn":[3.404384724],"iteration":762,"passed_time":0.3353615577,"remaining_time":0.1041686621},
{"learn":[3.403041656],"iteration":763,"passed_time":0.3356703057,"remaining_time":0.1036887332},
{"learn":[3.401101731],"iteration":764,"passed_time":0.3360517198,"remaining_time":0.103231574},
{"learn":[3.400890668],"iteration":765,"passed_time":0.3364028008,"remaining_time":0.1027653465},
{"learn":[3.399289941],"iteration":766,"passed_time":0.336819298,"remaining_time":0.1023192913},
{"learn":[3.399202366],"iteration":767,"passed_time":0.3370459632,"remaining_time":0.101815968},
{"learn":[3.397447845],"iteration":768,"passed_time":0.33727517,"remaining_time":0.1013141278},
{"learn":[3.394655341],"iteration":769,"passed_time":0.3375162934,"remaining_time":0.1008165552},
{"learn":[3.393228229],"iteration":770,"passed_time":0.3377521251,"remaining_time":0.1003180761},
{"learn":[3.389691197],"iteration":771,"passed_time":0.3379919569,"remaining_time":0.09982145876},
{"learn":[3.389626772],"iteration":772,"passed_time":0.338227747,"remaining_time":0.09932431896},
{"learn":[3.388480222],"iteration":773,"passed_time":0.3384622037,"remaining_time":0.09882746517},
{"learn":[3.388215066],"iteration":774,"passed_time":0.3386993271,"remaining_time":0.09833206272},
{"learn":[3.386324358],"iteration":775,"passed_time":0.3389323673,"remaining_time":0.09783614725},
{"learn":[3.383913061],"iteration":776,"passed_time":0.3391718657,"remaining_time":0.09734276196},
{"learn":[3.382839768],"iteration":777,"passed_time":0.3394081141,"remaining_time":0.09684910196},
{"learn":[3.381961844],"iteration":778,"passed_time":0.3396866122,"remaining_time":0.09636808896},
{"learn":[3.381521703],"iteration":779,"passed_time":0.3399331106,"remaining_time":0.09587856965},
{"learn":[3.380918963],"iteration":780,"passed_time":0.3401666507,"remaining_time":0.09538603906},
{"learn":[3.377139006],"iteration":781,"passed_time":0.3404783986,"remaining_time":0.09491597302},
{"learn":[3.376004372],"iteration":782,"passed_time":0.340822313,"remaining_time":0.09445522595},
{"learn":[3.373826468],"iteration":783,"passed_time":0.3412436852,"remaining_time":0.09401611735},
{"learn":[3.373546786],"iteration":784,"passed_time":0.3416244743,"remaining_time":0.09356593883},
{"learn":[3.372109181],"iteration":785,"passed_time":0.3419760553,"remaining_time":0.09310798453},
{"learn":[3.370764924],"iteration":786,"passed_time":0.3422993032,"remaining_time":0.09264263224},
{"learn":[3.367833107],"iteration":787,"passed_time":0.3426422592,"remaining_time":0.09218294283},
{"learn":[3.36450404],"iteration":788,"passed_time":0.3429732987,"remaining_time":0.09172036251},
{"learn":[3.361794558],"iteration":789,"passed_time":0.3432563385,"remaining_time":0.09124535579},
{"learn":[3.356880529],"iteration":790,"passed_time":0.3435423365,"remaining_time":0.0907716161},
{"learn":[3.353843509],"iteration":791,"passed_time":0.3438911259,"remaining_time":0.09031484114},
{"learn":[3.353640253],"iteration":792,"passed_time":0.3442693734,"remaining_time":0.08986602811},
{"learn":[3.353055088],"iteration":793,"passed_time":0.3445718297,"remaining_time":0.08939772911},
{"learn":[3.351415617],"iteration":794,"passed_time":0.3448216614,"remaining_time":0.08891627746},
{"learn":[3.349169061],"iteration":795,"passed_time":0.3451101594,"remaining_time":0.08844531724},
{"learn":[3.346211014],"iteration":796,"passed_time":0.3453951992,"remaining_time":0.08797393405},
{"learn":[3.344560452],"iteration":797,"passed_time":0.3457096554,"remaining_time":0.08751046416},
{"learn":[3.344445461],"iteration":798,"passed_time":0.3459953202,"remaining_time":0.08704012436},
{"learn":[3.342608898],"iteration":799,"passed_time":0.3462982765,"remaining_time":0.08657456913},
{"learn":[3.339572899],"iteration":800,"passed_time":0.3466553991,"remaining_time":0.08612287694},
{"learn":[3.339309302],"iteration":801,"passed_time":0.346977647,"remaining_time":0.08566281061},
{"learn":[3.33698088],"iteration":802,"passed_time":0.3473577278,"remaining_time":0.08521727569},
{"learn":[3.334746342],"iteration":803,"passed_time":0.3476208927,"remaining_time":0.08474340171},
{"learn":[3.332048511],"iteration":804,"passed_time":0.3479118908,"remaining_time":0.08427679342},
{"learn":[3.331932544],"iteration":805,"passed_time":0.3481821806,"remaining_time":0.08380563653},
{"learn":[3.330541133],"iteration":806,"passed_time":0.3485035952,"remaining_time":0.0833472043},
{"learn":[3.329124989],"iteration":807,"passed_time":0.3488208847,"remaining_time":0.08288813102},
{"learn":[3.32583918],"iteration":808,"passed_time":0.3491788407,"remaining_time":0.08243900935},
{"learn":[3.325287299],"iteration":809,"passed_time":0.3495252134,"remaining_time":0.08198739573},
{"learn":[3.322745162],"iteration":810,"passed_time":0.3498952942,"remaining_time":0.08154156672},
{"learn":[3.319733662],"iteration":811,"passed_time":0.3502174171,"remaining_time":0.0810848207},
{"learn":[3.318080007],"iteration":812,"passed_time":0.3505648731,"remaining_time":0.0806342328},
{"learn":[3.317179538],"iteration":813,"passed_time":0.3509456622,"remaining_time":0.08019151496},
{"learn":[3.315685949],"iteration":814,"passed_time":0.3513582428,"remaining_time":0.07975616555},
{"learn":[3.314944576],"iteration":815,"passed_time":0.351688574,"remaining_time":0.0793023255},
{"learn":[3.312369052],"iteration":816,"passed_time":0.3520391133,"remaining_time":0.07885331424},
{"learn":[3.312321621],"iteration":817,"passed_time":0.35227757,"remaining_time":0.07837960605},
{"learn":[3.309465776],"iteration":818,"passed_time":0.3526346093,"remaining_time":0.07793267923},
{"learn":[3.308307377],"iteration":819,"passed_time":0.352938899,"remaining_time":0.07747439245},
{"learn":[3.308076804],"iteration":820,"passed_time":0.3532953966,"remaining_time":0.07702786357},
{"learn":[3.305643326],"iteration":821,"passed_time":0.3536604358,"remaining_time":0.07658340338},
{"learn":[3.304154814],"iteration":822,"passed_time":0.3540772664,"remaining_time":0.07615027478},
{"learn":[3.303076321],"iteration":823,"passed_time":0.3544130558,"remaining_time":0.075699876},
{"learn":[3.301746372],"iteration":824,"passed_time":0.354733137,"remaining_time":0.075246423},
{"learn":[3.301345455],"iteration":825,"passed_time":0.355033385,"remaining_time":0.074789115},
{"learn":[3.299181039],"iteration":826,"passed_time":0.3553942576,"remaining_time":0.07434486888},
{"learn":[3.297989357],"iteration":827,"passed_time":0.3558101715,"remaining_time":0.07391225785},
{"learn":[3.294775182],"iteration":828,"passed_time":0.3561681691,"remaining_time":0.07346774055},
{"learn":[3.293840636],"iteration":829,"passed_time":0.3565651665,"remaining_time":0.07303141964},
{"learn":[3.289279397],"iteration":830,"passed_time":0.356934289,"remaining_time":0.07258952448},
{"learn":[3.286204979],"iteration":831,"passed_time":0.3572516202,"remaining_time":0.07213734639},
{"learn":[3.284833593],"iteration":832,"passed_time":0.3575724098,"remaining_time":0.07168618539},
{"learn":[3.283519914],"iteration":833,"passed_time":0.3579038242,"remaining_time":0.07123745182},
{"learn":[3.282853026],"iteration":834,"passed_time":0.3582591968,"remaining_time":0.07079373351},
{"learn":[3.281944673],"iteration":835,"passed_time":0.3586987356,"remaining_time":0.0703667376},
{"learn":[3.279764865],"iteration":836,"passed_time":0.3590715248,"remaining_time":0.06992671271},
{"learn":[3.277468839],"iteration":837,"passed_time":0.3594588972,"remaining_time":0.06948966748},
{"learn":[3.277124974],"iteration":838,"passed_time":0.3597734784,"remaining_time":0.06903877238},
{"learn":[3.275636037],"iteration":839,"passed_time":0.360087893,"remaining_time":0.0685881701},
{"learn":[3.274413635],"iteration":840,"passed_time":0.3604832654,"remaining_time":0.06815319761},
{"learn":[3.272636087],"iteration":841,"passed_time":0.3608395547,"remaining_time":0.06771098532},
{"learn":[3.269644466],"iteration":842,"passed_time":0.3611970106,"remaining_time":0.06726919415},
{"learn":[3.26852083],"iteration":843,"passed_time":0.3615124252,"remaining_time":0.06681983214},
{"learn":[3.267820927],"iteration":844,"passed_time":0.3618597979,"remaining_time":0.06637664931},
{"learn":[3.267331099],"iteration":845,"passed_time":0.3622142122,"remaining_time":0.06593497479},
{"learn":[3.267231014],"iteration":846,"passed_time":0.3625391267,"remaining_time":0.06548817755},
{"learn":[3.267158695],"iteration":847,"passed_time":0.3628944576,"remaining_time":0.06504711977},
{"learn":[3.264718705],"iteration":848,"passed_time":0.3632208721,"remaining_time":0.06460112096},
{"learn":[3.261678512],"iteration":849,"passed_time":0.3635692031,"remaining_time":0.06415927114},
{"learn":[3.261368381],"iteration":850,"passed_time":0.3639409507,"remaining_time":0.06372174107},
{"learn":[3.260128799],"iteration":851,"passed_time":0.3643016566,"remaining_time":0.06328244739},
{"learn":[3.258972952],"iteration":852,"passed_time":0.364694279,"remaining_time":0.06284883823},
{"learn":[3.258724846],"iteration":853,"passed_time":0.3650934847,"remaining_time":0.06241645054},
{"learn":[3.25686724],"iteration":854,"passed_time":0.3654524406,"remaining_time":0.06197731449},
{"learn":[3.255750259],"iteration":855,"passed_time":0.3658230215,"remaining_time":0.06154032137},
{"learn":[3.254915866],"iteration":856,"passed_time":0.3661064779,"remaining_time":0.06108894556},
{"learn":[3.254348625],"iteration":857,"passed_time":0.3665000586,"remaining_time":0.06065618686},
{"learn":[3.253408514],"iteration":858,"passed_time":0.3669022643,"remaining_time":0.06022493511},
{"learn":[3.253291714],"iteration":859,"passed_time":0.3672682202,"remaining_time":0.05978784979},
{"learn":[3.250186342],"iteration":860,"passed_time":0.3676596342,"remaining_time":0.05935503967},
{"learn":[3.249141318],"iteration":861,"passed_time":0.3679950903,"remaining_time":0.05891336713},
{"learn":[3.246300388],"iteration":862,"passed_time":0.3683200465,"remaining_time":0.05847027389},
{"learn":[3.245205135],"iteration":863,"passed_time":0.368691294,"remaining_time":0.05803474073},
{"learn":[3.244403535],"iteration":864,"passed_time":0.3690358751,"remaining_time":0.05759519437},
{"learn":[3.244211781],"iteration":865,"passed_time":0.3693150399,"remaining_time":0.0571457452},
{"learn":[3.242286347],"iteration":866,"passed_time":0.3696324128,"remaining_time":0.05670255005},
{"learn":[3.239606746],"iteration":867,"passed_time":0.3699277858,"remaining_time":0.05625629922},
{"learn":[3.236773361],"iteration":868,"passed_time":0.3702862417,"remaining_time":0.05581990526},
{"learn":[3.234552446],"iteration":869,"passed_time":0.3706826558,"remaining_time":0.05538936235},
{"learn":[3.233724647],"iteration":870,"passed_time":0.3710610282,"remaining_time":0.05495622577},
{"learn":[3.230851485],"iteration":871,"passed_time":0.3715908997,"remaining_time":0.05454545317},
{"learn":[3.227728941],"iteration":872,"passed_time":0.3721919374,"remaining_time":0.05414476065},
{"learn":[3.225787575],"iteration":873,"passed_time":0.3724918937,"remaining_time":0.05370020436},
{"learn":[3.222797487],"iteration":874,"passed_time":0.3728553496,"remaining_time":0.05326504995},
{"learn":[3.22137014],"iteration":875,"passed_time":0.3732068889,"remaining_time":0.05282837241},
{"learn":[3.219701963],"iteration":876,"passed_time":0.3735873864,"remaining_time":0.05239595043},
{"learn":[3.21783327],"iteration":877,"passed_time":0.3739705505,"remaining_time":0.05196401727},
{"learn":[3.217713355],"iteration":878,"passed_time":0.374300715,"remaining_time":0.05152489933},
{"learn":[3.217666091],"iteration":879,"passed_time":0.3746402127,"remaining_time":0.05108730174},
{"learn":[3.214962005],"iteration":880,"passed_time":0.3750772515,"remaining_time":0.05066310207},
{"learn":[3.214081828],"iteration":881,"passed_time":0.3753659162,"remaining_time":0.05021902281},
{"learn":[3.213358337],"iteration":882,"passed_time":0.3757636636,"remaining_time":0.04978974931},
{"learn":[3.210850401],"iteration":883,"passed_time":0.3760884114,"remaining_time":0.04935096801},
{"learn":[3.207810328],"iteration":884,"passed_time":0.3764703255,"remaining_time":0.04891987281},
{"learn":[3.204935073],"iteration":885,"passed_time":0.3768472814,"remaining_time":0.04848825065},
{"learn":[3.20280198],"iteration":886,"passed_time":0.3772187789,"remaining_time":0.04805605639},
{"learn":[3.200663495],"iteration":887,"passed_time":0.3775167352,"remaining_time":0.04761472336},
{"learn":[3.197301669],"iteration":888,"passed_time":0.3779279408,"remaining_time":0.04718785313},
{"learn":[3.195666943],"iteration":889,"passed_time":0.3782702302,"remaining_time":0.04675250036},
{"learn":[3.193886506],"iteration":890,"passed_time":0.3785996864,"remaining_time":0.04631578655},
{"learn":[3.190601248],"iteration":891,"passed_time":0.378957309,"remaining_time":0.04588272351},
{"learn":[3.188983797],"iteration":892,"passed_time":0.3792397238,"remaining_time":0.04544081796},
{"learn":[3.187365749],"iteration":893,"passed_time":0.3795909714,"remaining_time":0.04500743062},
{"learn":[3.186160771],"iteration":894,"passed_time":0.3799049693,"remaining_time":0.04456985674},
{"learn":[3.185358981],"iteration":895,"passed_time":0.3801974257,"remaining_time":0.04413005834},
{"learn":[3.183832164],"iteration":896,"passed_time":0.3805732982,"remaining_time":0.04370016691},
{"learn":[3.183106966],"iteration":897,"passed_time":0.3809735039,"remaining_time":0.04327315968},
{"learn":[3.182838152],"iteration":898,"passed_time":0.3813810428,"remaining_time":0.04284703596},
{"learn":[3.180835453],"iteration":899,"passed_time":0.3817567487,"remaining_time":0.04241741652},
{"learn":[3.179957348],"iteration":900,"passed_time":0.3820935797,"remaining_time":0.04198364528},
{"learn":[3.179752966],"iteration":901,"passed_time":0.3824332441,"remaining_time":0.04155039681},
{"learn":[3.178851983],"iteration":902,"passed_time":0.3827525754,"remaining_time":0.04111517144},
{"learn":[3.176748586],"iteration":903,"passed_time":0.3831169896,"remaining_time":0.04068499005},
{"learn":[3.172960988],"iteration":904,"passed_time":0.3834914454,"remaining_time":0.04025600808},
{"learn":[3.172794225],"iteration":905,"passed_time":0.3838607763,"remaining_time":0.03982661476},
{"learn":[3.169996507],"iteration":906,"passed_time":0.3850316435,"remaining_time":0.03947954007},
{"learn":[3.16813015],"iteration":907,"passed_time":0.3853768079,"remaining_time":0.03904698934},
{"learn":[3.166920871],"iteration":908,"passed_time":0.3856842225,"remaining_time":0.03861085176},
{"learn":[3.16531606],"iteration":909,"passed_time":0.3860461367,"remaining_time":0.03818038715},
{"learn":[3.162035247],"iteration":910,"passed_time":0.3864022594,"remaining_time":0.03774950723},
{"learn":[3.16189467],"iteration":911,"passed_time":0.3868197566,"remaining_time":0.03732471336},
{"learn":[3.161008416],"iteration":912,"passed_time":0.3871839208,"remaining_time":0.03689485335},
{"learn":[3.160560787],"iteration":913,"passed_time":0.3875351685,"remaining_time":0.03646392176},
{"learn":[3.160416261],"iteration":914,"passed_time":0.3878622497,"remaining_time":0.03603091937},
{"learn":[3.15844291],"iteration":915,"passed_time":0.3882684136,"remaining_time":0.03560540037},
{"learn":[3.155040501],"iteration":916,"passed_time":0.3885877865,"remaining_time":0.03517206792},
{"learn":[3.154937548],"iteration":917,"passed_time":0.3889507424,"remaining_time":0.03474287677},
{"learn":[3.153721161],"iteration":918,"passed_time":0.3892385738,"remaining_time":0.03430720836},
{"learn":[3.153170511],"iteration":919,"passed_time":0.3895002804,"remaining_time":0.0338695896},
{"learn":[3.153113601],"iteration":920,"passed_time":0.3898488614,"remaining_time":0.03343980462},
{"learn":[3.150607379],"iteration":921,"passed_time":0.390211484,"remaining_time":0.03301138368},
{"learn":[3.148408359],"iteration":922,"passed_time":0.3905873982,"remaining_time":0.03258421415},
{"learn":[3.147495728],"iteration":923,"passed_time":0.3909266876,"remaining_time":0.03215414313},
{"learn":[3.146946235],"iteration":924,"passed_time":0.3912224356,"remaining_time":0.03172073802},
{"learn":[3.14472738],"iteration":925,"passed_time":0.3915746416,"remaining_time":0.03129214198},
{"learn":[3.144469477],"iteration":926,"passed_time":0.3919152643,"remaining_time":0.03086279859},
{"learn":[3.142975516],"iteration":927,"passed_time":0.3922713869,"remaining_time":0.03043484899},
{"learn":[3.14079113],"iteration":928,"passed_time":0.3926156763,"remaining_time":0.03000614964},
{"learn":[3.138173032],"iteration":929,"passed_time":0.3930951731,"remaining_time":0.02958780873},
{"learn":[3.136352813],"iteration":930,"passed_time":0.3934563374,"remaining_time":0.02916056636},
{"learn":[3.133735004],"iteration":931,"passed_time":0.3938585847,"remaining_time":0.02873646326},
{"learn":[3.1319496],"iteration":932,"passed_time":0.3942168323,"remaining_time":0.02830924734},
{"learn":[3.129865343],"iteration":933,"passed_time":0.3945967881,"remaining_time":0.02788371308},
{"learn":[3.129830206],"iteration":934,"passed_time":0.3948730363,"remaining_time":0.02745106669},
{"learn":[3.126676562],"iteration":935,"passed_time":0.3952467838,"remaining_time":0.02702542111},
{"learn":[3.12645665],"iteration":936,"passed_time":0.3956301562,"remaining_time":0.02660053345},
{"learn":[3.126378007],"iteration":937,"passed_time":0.3959805289,"remaining_time":0.02617355308},
{"learn":[3.124621914],"iteration":938,"passed_time":0.3963389849,"remaining_time":0.025747261},
{"learn":[3.123379018],"iteration":939,"passed_time":0.3966105664,"remaining_time":0.02531556807},
{"learn":[3.123332451],"iteration":940,"passed_time":0.3969340226,"remaining_time":0.02488746794},
{"learn":[3.122432444],"iteration":941,"passed_time":0.3972662703,"remaining_time":0.02446013129},
{"learn":[3.121889006],"iteration":942,"passed_time":0.3976427678,"remaining_time":0.02403567101},
{"learn":[3.121070914],"iteration":943,"passed_time":0.3980051404,"remaining_time":0.02361047443},
{"learn":[3.118444705],"iteration":944,"passed_time":0.3983471381,"remaining_time":0.02318422497},
{"learn":[3.116820458],"iteration":945,"passed_time":0.3987080941,"remaining_time":0.02275923581},
{"learn":[3.114971041],"iteration":946,"passed_time":0.3990503835,"remaining_time":0.02233333719},
{"learn":[3.114685138],"iteration":947,"passed_time":0.3993611314,"remaining_time":0.02190588484},
{"learn":[3.113399363],"iteration":948,"passed_time":0.3997066708,"remaining_time":0.02148054816},
{"learn":[3.110575399],"iteration":949,"passed_time":0.4000343352,"remaining_time":0.0210544387},
{"learn":[3.110466553],"iteration":950,"passed_time":0.400422416,"remaining_time":0.02063164919},
{"learn":[3.108691641],"iteration":951,"passed_time":0.4007242473,"remaining_time":0.0202045839},
{"learn":[3.107898017],"iteration":952,"passed_time":0.4010966198,"remaining_time":0.01978126037},
{"learn":[3.105551729],"iteration":953,"passed_time":0.4014489091,"remaining_time":0.01935707528},
{"learn":[3.104824945],"iteration":954,"passed_time":0.4017777403,"remaining_time":0.01893193541},
{"learn":[3.103186704],"iteration":955,"passed_time":0.4021657377,"remaining_time":0.01850972015},
{"learn":[3.102330655],"iteration":956,"passed_time":0.4026235263,"remaining_time":0.01809071226},
{"learn":[3.102291298],"iteration":957,"passed_time":0.4030330653,"remaining_time":0.01766950808},
{"learn":[3.100363529],"iteration":958,"passed_time":0.4034169377,"remaining_time":0.01724723091},
{"learn":[3.097871596],"iteration":959,"passed_time":0.4037913519,"remaining_time":0.01682463966},
{"learn":[3.097372213],"iteration":960,"passed_time":0.4042060574,"remaining_time":0.01640378381},
{"learn":[3.095981813],"iteration":961,"passed_time":0.4046024715,"remaining_time":0.01598221821},
{"learn":[3.095347452],"iteration":962,"passed_time":0.404973719,"remaining_time":0.01555973791},
{"learn":[3.094728409],"iteration":963,"passed_time":0.4053857163,"remaining_time":0.01513888567},
{"learn":[3.094118537],"iteration":964,"passed_time":0.4057639637,"remaining_time":0.0147168277},
{"learn":[3.093793695],"iteration":965,"passed_time":0.4061128781,"remaining_time":0.01429382801},
{"learn":[3.092581602],"iteration":966,"passed_time":0.4064577924,"remaining_time":0.01387084504},
{"learn":[3.091694202],"iteration":967,"passed_time":0.406870498,"remaining_time":0.0134502644},
{"learn":[3.090298312],"iteration":968,"passed_time":0.407271287,"remaining_time":0.01302931878},
{"learn":[3.090020107],"iteration":969,"passed_time":0.4076119931,"remaining_time":0.01260655649},
{"learn":[3.088949869],"iteration":970,"passed_time":0.4080040321,"remaining_time":0.01218549633},
{"learn":[3.086700204],"iteration":971,"passed_time":0.4083829046,"remaining_time":0.01176411659},
{"learn":[3.086584317],"iteration":972,"passed_time":0.408779527,"remaining_time":0.01134331678},
{"learn":[3.084850742],"iteration":973,"passed_time":0.4091669827,"remaining_time":0.01092232192},
{"learn":[3.084239948],"iteration":974,"passed_time":0.4095199387,"remaining_time":0.01050051125},
{"learn":[3.082561673],"iteration":975,"passed_time":0.4099186861,"remaining_time":0.01007996769},
{"learn":[3.07991814],"iteration":976,"passed_time":0.4103573915,"remaining_time":0.009660409421},
{"learn":[3.079350277],"iteration":977,"passed_time":0.4107430556,"remaining_time":0.009239618837},
{"learn":[3.077637462],"iteration":978,"passed_time":0.4111408863,"remaining_time":0.008819160992},
{"learn":[3.076733301],"iteration":979,"passed_time":0.4115190087,"remaining_time":0.008398347117},
{"learn":[3.07594065],"iteration":980,"passed_time":0.4118655481,"remaining_time":0.007977008577},
{"learn":[3.072594655],"iteration":981,"passed_time":0.4122199207,"remaining_time":0.00755596596},
{"learn":[3.071977674],"iteration":982,"passed_time":0.4125454602,"remaining_time":0.00713456035},
{"learn":[3.069532634],"iteration":983,"passed_time":0.412931416,"remaining_time":0.006714331967},
{"learn":[3.068870784],"iteration":984,"passed_time":0.4132820387,"remaining_time":0.006293635106},
{"learn":[3.068801463],"iteration":985,"passed_time":0.4136375363,"remaining_time":0.005873149602},
{"learn":[3.067433249],"iteration":986,"passed_time":0.4139814507,"remaining_time":0.00545264322},
{"learn":[3.065611456],"iteration":987,"passed_time":0.4143489482,"remaining_time":0.005032578318},
{"learn":[3.063039162],"iteration":988,"passed_time":0.4147551955,"remaining_time":0.004613050708},
{"learn":[3.06177873],"iteration":989,"passed_time":0.4151131098,"remaining_time":0.004193061715},
{"learn":[3.061689148],"iteration":990,"passed_time":0.4154928156,"remaining_time":0.003773395903},
{"learn":[3.058984039],"iteration":991,"passed_time":0.4157524805,"remaining_time":0.003352842585},
{"learn":[3.057492984],"iteration":992,"passed_time":0.4161187281,"remaining_time":0.002933364649},
{"learn":[3.057290731],"iteration":993,"passed_time":0.4164864756,"remaining_time":0.002514002871},
{"learn":[3.056068348],"iteration":994,"passed_time":0.4168641815,"remaining_time":0.002094794882},
{"learn":[3.054987307],"iteration":995,"passed_time":0.4172372206,"remaining_time":0.001675651489},
{"learn":[3.054200234],"iteration":996,"passed_time":0.4175833433,"remaining_time":0.001256519589},
{"learn":[3.052732869],"iteration":997,"passed_time":0.4179961323,"remaining_time":0.0008376675997},
{"learn":[3.051787862],"iteration":998,"passed_time":0.4184242961,"remaining_time":0.0004188431392},
{"learn":[3.051366222],"iteration":999,"passed_time":0.4188220018,"remaining_time":0}
]}